{
    "Name": "每萬老人長期照顧、安養機構數",
    "Unit": "所/萬人",
    "Explain": "每萬名老人所享有之長期照顧、安養機構個數。",
    "ByYear": 111,
    "Total": "2.61",
    "Taiwan": "2.56",
    "NewTaipei": "3.08",
    "Taipei": "1.87",
    "Taoyuan": "2",
    "Taichung": "1.53",
    "Tainan": "3.35",
    "Kaohsiung": "3.04",
    "Ilan": "4.79",
    "HsinchuCounty": "2.27",
    "Miaoli": "1.33",
    "Changhwa": "2.23",
    "Nantou": "1.76",
    "Yunlin": "3.22",
    "ChiaYiCounty": "2.64",
    "Pingtung": "3.21",
    "Taitung": "3.01",
    "Hualien": "2.8",
    "Penghu": "1.53",
    "Keelung": "3.87",
    "HsinchuCity": "1.25",
    "ChiaYiCity": "2.58",
    "Kinmen": "0.86",
    "Matsu": "5.11"
}