{"Name":"å¹´é½¡åˆ¥å¤±æ¥­ç‡-65æ­²åŠä»¥ä¸Š","Unit":"ï¼…","Explain":"65æ­²åŠä»¥ä¸Šå¹´é½¡çµ„ä¹‹å¤±æ¥­ç‡ã€‚","ByYear":90,"Total":"...","Taiwan":"0.1","NewTaipei":"-","Taipei":"-","Taoyuan":"0.3","Taichung":"-","Tainan":"-","Kaohsiung":"0.1","Ilan":"-","HsinchuCounty":"-","Miaoli":"-","Changhwa":"0.2","Nantou":"-","Yunlin":"-","ChiaYiCounty":"-","Pingtung":"-","Taitung":"0.7","Hualien":"0.4","Penghu":"-","Keelung":"-","HsinchuCity":"0.1","ChiaYiCity":"-","Kinmen":"...","Matsu":"-"}‰ç¾©å¸‚":"-","é‡‘é–€ç¸£":"...","é€£æ±Ÿç¸£":"-"}