{"Name":"å¹¼å…’åœ’åœ’æ•¸","Unit":"æ‰€","Explain":"å„å…¬ç§ç«‹å¹¼å…’åœ’åœ’æ•¸ã€‚","ByYear":94,"Total":"3351","Taiwan":"3327","NewTaipei":"383","Taipei":"362","Taoyuan":"295","Taichung":"278","Tainan":"334","Kaohsiung":"396","Ilan":"59","HsinchuCounty":"112","Miaoli":"104","ChangHwa":"131","Nantou":"106","Yunlin":"116","ChiaYiCounty":"123","Pingtung":"136","Taitung":"81","Hualien":"90","Penghu":"15","Keelung":"66","HsinchuCity":"88","ChiaYiCity":"52","Kinmen":"19","Matsu":"5"}‰ç¾©å¸‚":"52","é‡‘é–€ç¸£":"19","é€£æ±Ÿç¸£":"5"}