{
    "Name": "沿岸漁業生產量",
    "Unit": "公噸",
    "Explain": "指使用船筏或不使用船筏在我國領海（12浬）內從事漁業者之生產量。",
    "ByYear": 112,
    "Total": "33479",
    "Taiwan": "32799",
    "NewTaipei": "1612",
    "Taipei": "-",
    "Taoyuan": "643",
    "Taichung": "501",
    "Tainan": "52",
    "Kaohsiung": "3582",
    "Ilan": "5103",
    "HsinchuCounty": "384",
    "Miaoli": "908",
    "Changhwa": "344",
    "Nantou": "-",
    "Yunlin": "401",
    "ChiaYiCounty": "62",
    "Pingtung": "1715",
    "Taitung": "2704",
    "Hualien": "2058",
    "Penghu": "847",
    "Keelung": "10942",
    "HsinchuCity": "940",
    "ChiaYiCity": "-",
    "Kinmen": "528",
    "Matsu": "152"
}