{"Name":"77歲人口數","Unit":"人","Explain":"於統計標準日戶籍登記實足年齡為77歲人口數。","ByYear":108,"Total":"121744","Taiwan":"121098","NewTaipei":"17959","Taipei":"15760","Taoyuan":"8565","Taichung":"11919","Tainan":"9671","Kaohsiung":"14529","Ilan":"2990","HsinchuCounty":"2636","Miaoli":"3367","ChangHwa":"7345","Nantou":"3286","Yunlin":"4811","ChiaYiCounty":"3670","Pingtung":"5211","Taitung":"1294","Hualien":"2065","Penghu":"536","Keelung":"2059","HsinchuCity":"1966","ChiaYiCity":"1459","Kinmen":"604","Matsu":"42"}市":"1459","金門縣":"604","連江縣":"42"}