{"Name":"å‡ºç”Ÿç™»è¨˜æ•¸","Unit":"äºº","Explain":"æˆ¶ç±ç•¶å¹´å‡ºç”Ÿç™»è¨˜äººå£æ•¸ã€‚","ByYear":103,"Total":"210383","Taiwan":"208715","NewTaipei":"38604","Taipei":"29024","Taoyuan":"17360","Taichung":"26194","Tainan":"15426","Kaohsiung":"22520","Ilan":"3527","HsinchuCounty":"5755","Miaoli":"6019","ChangHwa":"12033","Nantou":"3559","Yunlin":"5338","ChiaYiCounty":"2965","Pingtung":"5373","Taitung":"1739","Hualien":"2639","Penghu":"943","Keelung":"2062","HsinchuCity":"5503","ChiaYiCity":"2132","Kinmen":"1495","Matsu":"173"}‚":"2132","é‡‘é–€ç¸£":"1495","é€£æ±Ÿç¸£":"173"}