{
    "Name": "經常支出",
    "Unit": "百萬元",
    "Explain": "歲出中，除增置或擴充、改良資產及增加投資為資本支出外，餘均為經常支出。",
    "ByYear": 107,
    "Total": "864364.591",
    "Taiwan": "854046.524",
    "NewTaipei": "120918.624",
    "Taipei": "137471.091",
    "Taoyuan": "77881.3",
    "Taichung": "102149.368",
    "Tainan": "63594.609",
    "Kaohsiung": "105325.848",
    "Ilan": "16706.222",
    "HsinchuCounty": "16281.94",
    "Miaoli": "17194.656",
    "Changhwa": "34589.532",
    "Nantou": "17623.718",
    "Yunlin": "22290.144",
    "ChiaYiCounty": "18045.253",
    "Pingtung": "28325.228",
    "Taitung": "13271.132",
    "Hualien": "15078.495",
    "Penghu": "7263.114",
    "Keelung": "14194.189",
    "HsinchuCity": "15496.738",
    "ChiaYiCity": "10345.313",
    "Kinmen": "8084.118",
    "Matsu": "2233.947"
}