{"Name":"æµ·é¢é¤Šæ®–æ¼æ¥­ç”Ÿç”¢é‡","Unit":"å…¬å™¸","Explain":"æŒ‡åœ¨æ·ºæµ·å¾äº‹æ°´ç”¢å‹•æ¤ç‰©ä¹‹é¤Šè‚²æˆ–è“„é¤Šè€…ä¹‹ç”Ÿç”¢é‡ã€‚","ByYear":87,"Total":"...","Taiwan":"26034","NewTaipei":"-","Taipei":"-","Taoyuan":"-","Taichung":"63","Tainan":"5528","Kaohsiung":"35","Ilan":"-","HsinchuCounty":"-","Miaoli":"3","Changhwa":"6235","Nantou":"-","Yunlin":"3318","ChiaYiCounty":"6946","Pingtung":"1065","Taitung":"33","Hualien":"-","Penghu":"2735","Keelung":"-","HsinchuCity":"73","ChiaYiCity":"-","Kinmen":"...","Matsu":"..."}¾©å¸‚":"-","é‡‘é–€ç¸£":"...","é€£æ±Ÿç¸£":"..."}