{
    "Name": "公教人員人力素質－大專以上",
    "Unit": "％",
    "Explain": "公教人員大專畢業以上程度占公教人員之百分比。",
    "ByYear": 99,
    "Total": "89.83",
    "Taiwan": "89.87",
    "NewTaipei": "92.68",
    "Taipei": "92.22",
    "Taoyuan": "92.78",
    "Taichung": "91.26",
    "Tainan": "88.36",
    "Kaohsiung": "88.2",
    "Ilan": "88.61",
    "HsinchuCounty": "90.58",
    "Miaoli": "88.79",
    "Changhwa": "89.01",
    "Nantou": "86.39",
    "Yunlin": "87.49",
    "ChiaYiCounty": "87.08",
    "Pingtung": "84.62",
    "Taitung": "81.97",
    "Hualien": "86.12",
    "Penghu": "80.82",
    "Keelung": "90.05",
    "HsinchuCity": "91.29",
    "ChiaYiCity": "88.56",
    "Kinmen": "87.37",
    "Matsu": "74.28"
}281492707",
    "Hualien": "86.1196195389328",
    "Penghu": "80.8199121522694",
    "Keelung": "90.052641132692",
    "HsinchuCity": "91.2920287117492",
    "ChiaYiCity": "88.5560053981107",
    "Kinmen": "87.3657612128869",
    "Matsu": "74.2805755395683"
}