{
    "Name": "垃圾焚化量",
    "Unit": "公噸",
    "Explain": "一般廢棄物運送至垃圾焚化廠之處理量。88年以前為年度資料。",
    "ByYear": 109,
    "Total": "3789352",
    "Taiwan": "3780495",
    "NewTaipei": "530031",
    "Taipei": "225475",
    "Taoyuan": "407996",
    "Taichung": "496727",
    "Tainan": "368755",
    "Kaohsiung": "625485",
    "Ilan": "78572",
    "HsinchuCounty": "76991",
    "Miaoli": "94320",
    "Changhwa": "276033",
    "Nantou": "63523",
    "Yunlin": "50156",
    "ChiaYiCounty": "72294",
    "Pingtung": "131207",
    "Taitung": "3872",
    "Hualien": "32067",
    "Penghu": "21543",
    "Keelung": "95298",
    "HsinchuCity": "75908",
    "ChiaYiCity": "54242",
    "Kinmen": "6626",
    "Matsu": "2231"
}