{"Name":"營利事業營業家數","Unit":"家","Explain":"依加值型及非加值型營業稅法第五章第二十八條辦理營利事業稅籍登記之公司行號家數。","ByYear":92,"Total":"1108629","Taiwan":"1097440","NewTaipei":"166902","Taipei":"193403","Taoyuan":"75711","Taichung":"136011","Tainan":"85878","Kaohsiung":"130535","Ilan":"23389","HsinchuCounty":"17353","Miaoli":"23075","ChangHwa":"59413","Nantou":"21003","Yunlin":"25209","ChiaYiCounty":"17898","Pingtung":"35670","Taitung":"10845","Hualien":"17330","Penghu":"5331","Keelung":"16825","HsinchuCity":"20314","ChiaYiCity":"15345","Kinmen":"10309","Matsu":"880"}:"15345","金門縣":"10309","連江縣":"880"}