{"Name":"青壯年人口比率(15-64歲)","Unit":"％","Explain":"指15-64歲的人口占總人口之百分比。","ByYear":99,"Total":"73.61","Taiwan":"73.61","NewTaipei":"76.69","Taipei":"72.67","Taoyuan":"73.61","Taichung":"74.09","Tainan":"73.87","Kaohsiung":"74.96","Ilan":"71.64","HsinchuCounty":"69.94","Miaoli":"70.87","Changhwa":"71.64","Nantou":"71.63","Yunlin":"69.78","ChiaYiCounty":"70.34","Pingtung":"72.84","Taitung":"71.6","Hualien":"72.44","Penghu":"71.94","Keelung":"74.82","HsinchuCity":"71.48","ChiaYiCity":"71.59","Kinmen":"74.81","Matsu":"76.09"}71.59","金門縣":"74.81","連江縣":"76.09"}