{"Name":"幼年人口比率(0-14歲)","Unit":"％","Explain":"指0-14歲的人口占總人口之百分比。","ByYear":103,"Total":"13.99","Taiwan":"14","NewTaipei":"13.5","Taipei":"14.17","Taoyuan":"15.85","Taichung":"15.35","Tainan":"13.14","Kaohsiung":"13.06","Ilan":"13.18","HsinchuCounty":"17.37","Miaoli":"14.49","ChangHwa":"14.34","Nantou":"12.55","Yunlin":"13.16","ChiaYiCounty":"11.4","Pingtung":"12.1","Taitung":"13.24","Hualien":"13.16","Penghu":"11.95","Keelung":"11.61","HsinchuCity":"18.07","ChiaYiCity":"15.23","Kinmen":"10.92","Matsu":"12.75"}15.23","金門縣":"10.92","連江縣":"12.75"}