{"Name":"海面養殖漁業生產量占總漁業生產量比率","Unit":"％","Explain":"指海面養殖漁業生產量占漁業生產量之百分比。","ByYear":95,"Total":"4.18881222718111","Taiwan":"4.17604644616307","NewTaipei":"-","Taipei":"-","Taoyuan":"-","Taichung":"-","Tainan":"9.8612245710499","Kaohsiung":"-","Ilan":"-","HsinchuCounty":"-","Miaoli":"-","ChangHwa":"15.9505770308582","Nantou":"-","Yunlin":"12.5582656983189","ChiaYiCounty":"14.7004773640454","Pingtung":"0.888345922158788","Taitung":"0.00390959950355906","Hualien":"-","Penghu":"19.5094218602708","Keelung":"-","HsinchuCity":"0.176605639606758","ChiaYiCity":"-","Kinmen":"15.4976131135213","Matsu":"7.2908112754315"}5.4976131135213","連江縣":"7.2908112754315"}