{"Name":"家庭收支-平均每戶消費支出","Unit":"元","Explain":"平均每一戶之消費性支出總額。","ByYear":103,"Total":"...","Taiwan":"755169","NewTaipei":"760951","Taipei":"1014262","Taoyuan":"821381","Taichung":"786285","Tainan":"674797","Kaohsiung":"722305","Ilan":"738296","HsinchuCounty":"900922","Miaoli":"649705","ChangHwa":"594464","Nantou":"561412","Yunlin":"518443","ChiaYiCounty":"567649","Pingtung":"547989","Taitung":"494037","Hualien":"547353","Penghu":"543641","Keelung":"692416","HsinchuCity":"1036179","ChiaYiCity":"726313","Kinmen":"563569","Matsu":"546474"}313","金門縣":"563569","連江縣":"546474"}