{"Name":"å‹è³‡çˆ­è­°äººæ•¸","Unit":"äºº","Explain":"æŒ‡åƒèˆ‡å‹è³‡çˆ­è­°ä¹‹äººæ•¸ã€‚","ByYear":105,"Total":"35815","Taiwan":"35707","NewTaipei":"5707","Taipei":"6257","Taoyuan":"4707","Taichung":"4385","Tainan":"2642","Kaohsiung":"5106","Ilan":"627","HsinchuCounty":"1136","Miaoli":"561","ChangHwa":"1016","Nantou":"179","Yunlin":"369","ChiaYiCounty":"459","Pingtung":"706","Taitung":"95","Hualien":"377","Penghu":"136","Keelung":"383","HsinchuCity":"383","ChiaYiCity":"476","Kinmen":"105","Matsu":"3"}¾©å¸‚":"476","é‡‘é–€ç¸£":"105","é€£æ±Ÿç¸£":"3"}