{"Name":"每萬輛機動車肇事數","Unit":"件／萬輛","Explain":"每萬輛機動車輛的平均肇事件數；八十八年以前僅包含A1類。","ByYear":99,"Total":"101.94","Taiwan":"102.08","NewTaipei":"57.19","Taipei":"104.48","Taoyuan":"107.02","Taichung":"170.45","Tainan":"78.63","Kaohsiung":"108.26","Ilan":"116.1","HsinchuCounty":"117.46","Miaoli":"74.41","Changhwa":"92.59","Nantou":"86.09","Yunlin":"81.09","ChiaYiCounty":"67.81","Pingtung":"104.3","Taitung":"89.99","Hualien":"109.6","Penghu":"78.46","Keelung":"84.94","HsinchuCity":"144.69","ChiaYiCity":"115.49","Kinmen":"62.91","Matsu":"-"}":"115.49","金門縣":"62.91","連江縣":"-"}