{"Name":"67歲人口數","Unit":"人","Explain":"於統計標準日戶籍登記實足年齡為67歲人口數。","ByYear":102,"Total":"141870","Taiwan":"141107","NewTaipei":"22769","Taipei":"19695","Taoyuan":"10145","Taichung":"14332","Tainan":"10950","Kaohsiung":"17576","Ilan":"2796","HsinchuCounty":"2756","Miaoli":"3490","Changhwa":"7715","Nantou":"3564","Yunlin":"5684","ChiaYiCounty":"3501","Pingtung":"5595","Taitung":"1488","Hualien":"2344","Penghu":"789","Keelung":"2014","HsinchuCity":"2261","ChiaYiCity":"1643","Kinmen":"682","Matsu":"81"}市":"1643","金門縣":"682","連江縣":"81"}