{
    "1998": {
        "Name": "融資需求-債務之償還",
        "Unit": "百萬元",
        "Explain": "應償還之債款本金支出。",
        "ByYear": 87,
        "Total": "49411.362",
        "Taiwan": "49386.362",
        "NewTaipei": "191.666",
        "Taipei": "39912.669",
        "Taoyuan": "339.619",
        "Taichung": "1442.234",
        "Tainan": "1411.573",
        "Kaohsiung": "2868.335",
        "Ilan": "637.309",
        "HsinchuCounty": "77.046",
        "Miaoli": "322.945",
        "Changhwa": "385.891",
        "Nantou": "304.068",
        "Yunlin": "435.386",
        "ChiaYiCounty": "55.659",
        "Pingtung": "322.632",
        "Taitung": "185.38",
        "Hualien": "-",
        "Penghu": "56.265",
        "Keelung": "221.255",
        "HsinchuCity": "87.573",
        "ChiaYiCity": "128.851",
        "Kinmen": "25",
        "Matsu": "-"
    },
    "1999": {
        "Name": "融資需求-債務之償還",
        "Unit": "百萬元",
        "Explain": "應償還之債款本金支出。",
        "ByYear": 88,
        "Total": "30246.912",
        "Taiwan": "30171.912",
        "NewTaipei": "191.667",
        "Taipei": "17851.061",
        "Taoyuan": "353.7",
        "Taichung": "2002.307",
        "Tainan": "749.957",
        "Kaohsiung": "4768.945",
        "Ilan": "502.125",
        "HsinchuCounty": "364.998",
        "Miaoli": "338.836",
        "Changhwa": "685.605",
        "Nantou": "287.459",
        "Yunlin": "308.015",
        "ChiaYiCounty": "229.617",
        "Pingtung": "419.068",
        "Taitung": "193.399",
        "Hualien": "103.2",
        "Penghu": "33.39",
        "Keelung": "159.285",
        "HsinchuCity": "170.577",
        "ChiaYiCity": "458.696",
        "Kinmen": "75",
        "Matsu": "-"
    },
    "2000": {
        "Name": "融資需求-債務之償還",
        "Unit": "百萬元",
        "Explain": "應償還之債款本金支出。",
        "ByYear": 89,
        "Total": "35570.61",
        "Taiwan": "35383.11",
        "NewTaipei": "191.666",
        "Taipei": "13330.999",
        "Taoyuan": "495",
        "Taichung": "2959.756",
        "Tainan": "2701.279",
        "Kaohsiung": "7385.02",
        "Ilan": "736.974",
        "HsinchuCounty": "331.483",
        "Miaoli": "626.1",
        "Changhwa": "611.773",
        "Nantou": "360.331",
        "Yunlin": "438.148",
        "ChiaYiCounty": "2492.075",
        "Pingtung": "719.854",
        "Taitung": "148.682",
        "Hualien": "260.103",
        "Penghu": "52.105",
        "Keelung": "241.513",
        "HsinchuCity": "296.934",
        "ChiaYiCity": "1003.306",
        "Kinmen": "187.5",
        "Matsu": "-"
    },
    "2001": {
        "Name": "融資需求-債務之償還",
        "Unit": "百萬元",
        "Explain": "應償還之債款本金支出。",
        "ByYear": 90,
        "Total": "30676.234",
        "Taiwan": "30463.734",
        "NewTaipei": "697.867",
        "Taipei": "9650",
        "Taoyuan": "475",
        "Taichung": "3251.634",
        "Tainan": "2094.867",
        "Kaohsiung": "7398.514",
        "Ilan": "680.442",
        "HsinchuCounty": "592.096",
        "Miaoli": "722.202",
        "Changhwa": "601.493",
        "Nantou": "618.939",
        "Yunlin": "699.727",
        "ChiaYiCounty": "295.674",
        "Pingtung": "731.247",
        "Taitung": "446.66",
        "Hualien": "424.347",
        "Penghu": "63.725",
        "Keelung": "229.283",
        "HsinchuCity": "500.722",
        "ChiaYiCity": "289.29",
        "Kinmen": "212.5",
        "Matsu": "-"
    },
    "2002": {
        "Name": "融資需求-債務之償還",
        "Unit": "百萬元",
        "Explain": "應償還之債款本金支出。",
        "ByYear": 91,
        "Total": "30482.432",
        "Taiwan": "30482.432",
        "NewTaipei": "801.166",
        "Taipei": "5000",
        "Taoyuan": "500.532",
        "Taichung": "2488.544",
        "Tainan": "6751.437",
        "Kaohsiung": "5287.071",
        "Ilan": "805.373",
        "HsinchuCounty": "790.646",
        "Miaoli": "1261.313",
        "Changhwa": "1008.407",
        "Nantou": "850.035",
        "Yunlin": "578.83",
        "ChiaYiCounty": "520.151",
        "Pingtung": "328.42",
        "Taitung": "676.565",
        "Hualien": "1725.23",
        "Penghu": "55.04",
        "Keelung": "322.573",
        "HsinchuCity": "362.199",
        "ChiaYiCity": "368.895",
        "Kinmen": "-",
        "Matsu": "-"
    },
    "2003": {
        "Name": "融資需求-債務之償還",
        "Unit": "百萬元",
        "Explain": "應償還之債款本金支出。",
        "ByYear": 92,
        "Total": "33731.599",
        "Taiwan": "33731.599",
        "NewTaipei": "1502.366",
        "Taipei": "5132.866",
        "Taoyuan": "-",
        "Taichung": "3704.185",
        "Tainan": "3095.517",
        "Kaohsiung": "5497.644",
        "Ilan": "2202.809",
        "HsinchuCounty": "1108.883",
        "Miaoli": "1547.587",
        "Changhwa": "1015.223",
        "Nantou": "1023.355",
        "Yunlin": "1460.535",
        "ChiaYiCounty": "1105.856",
        "Pingtung": "1788.987",
        "Taitung": "581.047",
        "Hualien": "1209.93",
        "Penghu": "39.57",
        "Keelung": "859.891",
        "HsinchuCity": "454.012",
        "ChiaYiCity": "401.327",
        "Kinmen": "-",
        "Matsu": "-"
    },
    "2004": {
        "Name": "融資需求-債務之償還",
        "Unit": "百萬元",
        "Explain": "應償還之債款本金支出。",
        "ByYear": 93,
        "Total": "58164.459",
        "Taiwan": "58164.459",
        "NewTaipei": "1502.366",
        "Taipei": "5474.23",
        "Taoyuan": "9029.967",
        "Taichung": "4828.553",
        "Tainan": "7998.44",
        "Kaohsiung": "6397.923",
        "Ilan": "4853.898",
        "HsinchuCounty": "1891.361",
        "Miaoli": "2454.827",
        "Changhwa": "1325.209",
        "Nantou": "1588.755",
        "Yunlin": "1824.455",
        "ChiaYiCounty": "2193.196",
        "Pingtung": "1000",
        "Taitung": "450",
        "Hualien": "2450",
        "Penghu": "27.044",
        "Keelung": "953.008",
        "HsinchuCity": "1439.96",
        "ChiaYiCity": "481.261",
        "Kinmen": "-",
        "Matsu": "-"
    },
    "2005": {
        "Name": "融資需求-債務之償還",
        "Unit": "百萬元",
        "Explain": "應償還之債款本金支出。",
        "ByYear": 94,
        "Total": "59438.419",
        "Taiwan": "59438.419",
        "NewTaipei": "2523.466",
        "Taipei": "5167.292",
        "Taoyuan": "5150",
        "Taichung": "5950",
        "Tainan": "4512.047",
        "Kaohsiung": "7056.528",
        "Ilan": "2888.135",
        "HsinchuCounty": "3025.549",
        "Miaoli": "3666.617",
        "Changhwa": "1909.129",
        "Nantou": "2327.994",
        "Yunlin": "2933.566",
        "ChiaYiCounty": "3671.683",
        "Pingtung": "2902.337",
        "Taitung": "150",
        "Hualien": "3900",
        "Penghu": "4.25",
        "Keelung": "478.342",
        "HsinchuCity": "594.777",
        "ChiaYiCity": "626.703",
        "Kinmen": "-",
        "Matsu": "-"
    },
    "2006": {
        "Name": "融資需求-債務之償還",
        "Unit": "百萬元",
        "Explain": "應償還之債款本金支出。",
        "ByYear": 95,
        "Total": "80939.898",
        "Taiwan": "80939.898",
        "NewTaipei": "2454.956",
        "Taipei": "5558.334",
        "Taoyuan": "7425",
        "Taichung": "8275",
        "Tainan": "8807.44",
        "Kaohsiung": "8206.128",
        "Ilan": "3133.227",
        "HsinchuCounty": "3238",
        "Miaoli": "4275",
        "Changhwa": "3025.021",
        "Nantou": "3230.5",
        "Yunlin": "5701.248",
        "ChiaYiCounty": "4785.916",
        "Pingtung": "2746.554",
        "Taitung": "950",
        "Hualien": "4250",
        "Penghu": "-",
        "Keelung": "917.709",
        "HsinchuCity": "3477.371",
        "ChiaYiCity": "482.491",
        "Kinmen": "-",
        "Matsu": "-"
    },
    "2007": {
        "Name": "融資需求-債務之償還",
        "Unit": "百萬元",
        "Explain": "應償還之債款本金支出。",
        "ByYear": 96,
        "Total": "112243.767",
        "Taiwan": "112243.767",
        "NewTaipei": "21500",
        "Taipei": "13744.682",
        "Taoyuan": "7475",
        "Taichung": "8551.363",
        "Tainan": "7970.266",
        "Kaohsiung": "7188.424",
        "Ilan": "4460.961",
        "HsinchuCounty": "4728",
        "Miaoli": "3892",
        "Changhwa": "2705.166",
        "Nantou": "4105.5",
        "Yunlin": "5408.519",
        "ChiaYiCounty": "3696.729",
        "Pingtung": "4647.474",
        "Taitung": "3000",
        "Hualien": "4700",
        "Penghu": "-",
        "Keelung": "1140.433",
        "HsinchuCity": "2946.812",
        "ChiaYiCity": "382.434",
        "Kinmen": "-",
        "Matsu": "-"
    },
    "2008": {
        "Name": "融資需求-債務之償還",
        "Unit": "百萬元",
        "Explain": "應償還之債款本金支出。",
        "ByYear": 97,
        "Total": "118340.864",
        "Taiwan": "118340.864",
        "NewTaipei": "34635.303",
        "Taipei": "6600",
        "Taoyuan": "4750",
        "Taichung": "10094.122",
        "Tainan": "7098.123",
        "Kaohsiung": "9447.666",
        "Ilan": "3079.131",
        "HsinchuCounty": "3200",
        "Miaoli": "3967",
        "Changhwa": "2791.623",
        "Nantou": "4789.75",
        "Yunlin": "5725.479",
        "ChiaYiCounty": "6411.093",
        "Pingtung": "3101.97",
        "Taitung": "2936.767",
        "Hualien": "4834.151",
        "Penghu": "-",
        "Keelung": "1374.833",
        "HsinchuCity": "2922.714",
        "ChiaYiCity": "581.132",
        "Kinmen": "-",
        "Matsu": "-"
    },
    "2009": {
        "Name": "融資需求-債務之償還",
        "Unit": "百萬元",
        "Explain": "應償還之債款本金支出。",
        "ByYear": 98,
        "Total": "133870.08",
        "Taiwan": "133870.08",
        "NewTaipei": "34304.465",
        "Taipei": "6600",
        "Taoyuan": "7337.5",
        "Taichung": "10409.77",
        "Tainan": "13359.623",
        "Kaohsiung": "10472.221",
        "Ilan": "2775.997",
        "HsinchuCounty": "6578",
        "Miaoli": "5128.5",
        "Changhwa": "2813.964",
        "Nantou": "4664.75",
        "Yunlin": "6984.818",
        "ChiaYiCounty": "6081.937",
        "Pingtung": "4538.552",
        "Taitung": "3433.64",
        "Hualien": "2124.151",
        "Penghu": "30",
        "Keelung": "1658.215",
        "HsinchuCity": "3402.835",
        "ChiaYiCity": "1171.138",
        "Kinmen": "-",
        "Matsu": "-"
    },
    "2010": {
        "Name": "融資需求-債務之償還",
        "Unit": "百萬元",
        "Explain": "應償還之債款本金支出。",
        "ByYear": 99,
        "Total": "144932.493",
        "Taiwan": "144932.493",
        "NewTaipei": "35507.316",
        "Taipei": "6600",
        "Taoyuan": "8087.5",
        "Taichung": "10803.613",
        "Tainan": "10929.318",
        "Kaohsiung": "11412.167",
        "Ilan": "5465.743",
        "HsinchuCounty": "4178",
        "Miaoli": "5571.11",
        "Changhwa": "3280.63",
        "Nantou": "3976",
        "Yunlin": "6511.712",
        "ChiaYiCounty": "6462.718",
        "Pingtung": "6782.33",
        "Taitung": "2965.098",
        "Hualien": "4910",
        "Penghu": "900",
        "Keelung": "2144.785",
        "HsinchuCity": "3012.05",
        "ChiaYiCity": "1089.818",
        "Kinmen": "-",
        "Matsu": "-"
    },
    "2011": {
        "Name": "融資需求-債務之償還",
        "Unit": "百萬元",
        "Explain": "應償還之債款本金支出。",
        "ByYear": 100,
        "Total": "158200.238",
        "Taiwan": "158200.238",
        "NewTaipei": "34600",
        "Taipei": "6600",
        "Taoyuan": "8850",
        "Taichung": "12773.57",
        "Tainan": "21196.314",
        "Kaohsiung": "8344.969",
        "Ilan": "13029.729",
        "HsinchuCounty": "5938",
        "Miaoli": "8265.713",
        "Changhwa": "3393.095",
        "Nantou": "3845",
        "Yunlin": "6990.023",
        "ChiaYiCounty": "7274.666",
        "Pingtung": "3491.626",
        "Taitung": "4345.098",
        "Hualien": "2648.303",
        "Penghu": "170",
        "Keelung": "2409.74",
        "HsinchuCity": "3156.113",
        "ChiaYiCity": "878.272",
        "Kinmen": "-",
        "Matsu": "-"
    },
    "2012": {
        "Name": "融資需求-債務之償還",
        "Unit": "百萬元",
        "Explain": "應償還之債款本金支出。",
        "ByYear": 101,
        "Total": "166037.536",
        "Taiwan": "166037.536",
        "NewTaipei": "18100",
        "Taipei": "6600",
        "Taoyuan": "10500",
        "Taichung": "27873.926",
        "Tainan": "19541.083",
        "Kaohsiung": "9029.65",
        "Ilan": "10204.777",
        "HsinchuCounty": "7128",
        "Miaoli": "8750.138",
        "Changhwa": "5833.333",
        "Nantou": "4806",
        "Yunlin": "7224.17",
        "ChiaYiCounty": "8185.716",
        "Pingtung": "4869.996",
        "Taitung": "3747.931",
        "Hualien": "5664.151",
        "Penghu": "1400",
        "Keelung": "2660.807",
        "HsinchuCity": "3116.493",
        "ChiaYiCity": "801.359",
        "Kinmen": "-",
        "Matsu": "-"
    },
    "2013": {
        "Name": "融資需求-債務之償還",
        "Unit": "百萬元",
        "Explain": "應償還之債款本金支出。",
        "ByYear": 102,
        "Total": "210181.969",
        "Taiwan": "210181.969",
        "NewTaipei": "45800",
        "Taipei": "6600",
        "Taoyuan": "11875",
        "Taichung": "31522.419",
        "Tainan": "25706.403",
        "Kaohsiung": "9711.97",
        "Ilan": "13310.961",
        "HsinchuCounty": "10398",
        "Miaoli": "9217.106",
        "Changhwa": "3583.333",
        "Nantou": "5130.75",
        "Yunlin": "8679.599",
        "ChiaYiCounty": "7568.925",
        "Pingtung": "6999.805",
        "Taitung": "3055.931",
        "Hualien": "3564.151",
        "Penghu": "170",
        "Keelung": "2330.597",
        "HsinchuCity": "4488.042",
        "ChiaYiCity": "468.971",
        "Kinmen": "-",
        "Matsu": "-"
    },
    "2014": {
        "Name": "融資需求-債務之償還",
        "Unit": "百萬元",
        "Explain": "應償還之債款本金支出。",
        "ByYear": 103,
        "Total": "212478.325",
        "Taiwan": "212478.325",
        "NewTaipei": "39000",
        "Taipei": "17200",
        "Taoyuan": "7675",
        "Taichung": "33913.919",
        "Tainan": "21145.19",
        "Kaohsiung": "3141.994",
        "Ilan": "13450.806",
        "HsinchuCounty": "13370",
        "Miaoli": "9792.856",
        "Changhwa": "4600",
        "Nantou": "4564.44",
        "Yunlin": "12397.847",
        "ChiaYiCounty": "8944.75",
        "Pingtung": "5775.782",
        "Taitung": "3055.931",
        "Hualien": "4900",
        "Penghu": "1400",
        "Keelung": "3376.597",
        "HsinchuCity": "4245.671",
        "ChiaYiCity": "527.538",
        "Kinmen": "-",
        "Matsu": "-"
    },
    "2015": {
        "Name": "融資需求-債務之償還",
        "Unit": "百萬元",
        "Explain": "應償還之債款本金支出。",
        "ByYear": 104,
        "Total": "248642.552",
        "Taiwan": "248642.552",
        "NewTaipei": "38441.397",
        "Taipei": "18600",
        "Taoyuan": "16600",
        "Taichung": "47552.169",
        "Tainan": "24533.313",
        "Kaohsiung": "3499.977",
        "Ilan": "13141.268",
        "HsinchuCounty": "13610",
        "Miaoli": "9650.08",
        "Changhwa": "6950",
        "Nantou": "4670.44",
        "Yunlin": "14597.415",
        "ChiaYiCounty": "8763.125",
        "Pingtung": "7242.346",
        "Taitung": "3802.291",
        "Hualien": "3260",
        "Penghu": "940",
        "Keelung": "3427.435",
        "HsinchuCity": "8910.851",
        "ChiaYiCity": "450.439",
        "Kinmen": "-",
        "Matsu": "-"
    },
    "2016": {
        "Name": "融資需求-債務之償還",
        "Unit": "百萬元",
        "Explain": "應償還之債款本金支出。",
        "ByYear": 105,
        "Total": "272964.755",
        "Taiwan": "272964.755",
        "NewTaipei": "56000",
        "Taipei": "14466.971",
        "Taoyuan": "17600",
        "Taichung": "56529.265",
        "Tainan": "24264.8",
        "Kaohsiung": "3499.93",
        "Ilan": "13708.466",
        "HsinchuCounty": "15470",
        "Miaoli": "8631.238",
        "Changhwa": "9487.333",
        "Nantou": "4846.58",
        "Yunlin": "11949.142",
        "ChiaYiCounty": "8740",
        "Pingtung": "5298.846",
        "Taitung": "4010.833",
        "Hualien": "4880",
        "Penghu": "1400",
        "Keelung": "2747.88",
        "HsinchuCity": "9193.195",
        "ChiaYiCity": "240.273",
        "Kinmen": "-",
        "Matsu": "-"
    },
    "2017": {
        "Name": "融資需求-債務之償還",
        "Unit": "百萬元",
        "Explain": "應償還之債款本金支出。",
        "ByYear": 106,
        "Total": "304934.578",
        "Taiwan": "304934.578",
        "NewTaipei": "92500",
        "Taipei": "11600",
        "Taoyuan": "15000",
        "Taichung": "60500",
        "Tainan": "32147.9",
        "Kaohsiung": "3549.99",
        "Ilan": "13036.759",
        "HsinchuCounty": "13490",
        "Miaoli": "8807.659",
        "Changhwa": "6879.333",
        "Nantou": "4695.08",
        "Yunlin": "12443.278",
        "ChiaYiCounty": "8030",
        "Pingtung": "3967.748",
        "Taitung": "3873.718",
        "Hualien": "3500",
        "Penghu": "650",
        "Keelung": "2666.093",
        "HsinchuCity": "7510",
        "ChiaYiCity": "87.017",
        "Kinmen": "-",
        "Matsu": "-"
    },
    "2018": {
        "Name": "融資需求-債務之償還",
        "Unit": "百萬元",
        "Explain": "應償還之債款本金支出。",
        "ByYear": 107,
        "Total": "316422.399",
        "Taiwan": "316422.399",
        "NewTaipei": "94300",
        "Taipei": "14569.051",
        "Taoyuan": "20000",
        "Taichung": "62500",
        "Tainan": "23324.8",
        "Kaohsiung": "3699.932",
        "Ilan": "10981.728",
        "HsinchuCounty": "17690",
        "Miaoli": "9335.656",
        "Changhwa": "6636.666",
        "Nantou": "4534.35",
        "Yunlin": "12058.21",
        "ChiaYiCounty": "6968.75",
        "Pingtung": "9118.162",
        "Taitung": "3962.885",
        "Hualien": "5560",
        "Penghu": "1000",
        "Keelung": "2652.093",
        "HsinchuCity": "7500",
        "ChiaYiCity": "30.112",
        "Kinmen": "-",
        "Matsu": "-"
    },
    "2019": {
        "Name": "融資需求-債務之償還",
        "Unit": "百萬元",
        "Explain": "應償還之債款本金支出。",
        "ByYear": 108,
        "Total": "319389.006",
        "Taiwan": "319389.006",
        "NewTaipei": "85830.548",
        "Taipei": "7580.296",
        "Taoyuan": "20000",
        "Taichung": "88000",
        "Tainan": "32147.9",
        "Kaohsiung": "3699.855",
        "Ilan": "6650",
        "HsinchuCounty": "12230",
        "Miaoli": "9530.951",
        "Changhwa": "7983.333",
        "Nantou": "4409.31",
        "Yunlin": "11600.243",
        "ChiaYiCounty": "7475",
        "Pingtung": "4200",
        "Taitung": "4062.885",
        "Hualien": "2670",
        "Penghu": "190",
        "Keelung": "2800",
        "HsinchuCity": "8328.682",
        "ChiaYiCity": "-",
        "Kinmen": "-",
        "Matsu": "-"
    }
}