{
    "Name": "竊盜犯罪人口率",
    "Unit": "人/十萬人",
    "Explain": "每十萬人口中竊盜嫌疑犯人數。",
    "ByYear": 99,
    "Total": "162.28",
    "Taiwan": "162.65",
    "NewTaipei": "141.91",
    "Taipei": "104.05",
    "Taoyuan": "170.57",
    "Taichung": "154.31",
    "Tainan": "115.06",
    "Kaohsiung": "176.72",
    "Ilan": "184.36",
    "HsinchuCounty": "167.99",
    "Miaoli": "263.11",
    "Changhwa": "171.85",
    "Nantou": "165.32",
    "Yunlin": "144.12",
    "ChiaYiCounty": "179.47",
    "Pingtung": "223.9",
    "Taitung": "132.56",
    "Hualien": "365.42",
    "Penghu": "162.59",
    "Keelung": "198.07",
    "HsinchuCity": "193.73",
    "ChiaYiCity": "244.58",
    "Kinmen": "82.65",
    "Matsu": "90.62"
}Hualien": "365.41825237691",
    "Penghu": "162.586471148668",
    "Keelung": "198.069790473231",
    "HsinchuCity": "193.728376369975",
    "ChiaYiCity": "244.57621130213",
    "Kinmen": "82.6502482122961",
    "Matsu": "90.6207521522429"
}