{
    "Name": "教育程度別失業率-國中及以下",
    "Unit": "％",
    "Explain": "國中及以下程度者之失業率。",
    "ByYear": 105,
    "Total": "-",
    "Taiwan": "3.1",
    "NewTaipei": "3",
    "Taipei": "3.7",
    "Taoyuan": "4.9",
    "Taichung": "1.9",
    "Tainan": "2.9",
    "Kaohsiung": "3.6",
    "Ilan": "5.2",
    "HsinchuCounty": "3.5",
    "Miaoli": "2.7",
    "Changhwa": "2.1",
    "Nantou": "2.3",
    "Yunlin": "2.5",
    "ChiaYiCounty": "3.1",
    "Pingtung": "2.4",
    "Taitung": "2.7",
    "Hualien": "5.8",
    "Penghu": "0.2",
    "Keelung": "4.3",
    "HsinchuCity": "5.6",
    "ChiaYiCity": "3.7",
    "Kinmen": "0.2",
    "Matsu": "0.3"
}