{
    "Name": "歲入來源別-補助及協助收入",
    "Unit": "百萬元",
    "Explain": "上級政府對下級政府之移轉稱為補助，反之則為協助。",
    "ByYear": 103,
    "Total": "288689.34",
    "Taiwan": "283196.9",
    "NewTaipei": "29196.9",
    "Taipei": "23732.02",
    "Taoyuan": "13458.76",
    "Taichung": "21726.6",
    "Tainan": "23434.29",
    "Kaohsiung": "27855.01",
    "Ilan": "9329.62",
    "HsinchuCounty": "8286.75",
    "Miaoli": "10938.78",
    "Changhwa": "17626.2",
    "Nantou": "12327.95",
    "Yunlin": "12954.2",
    "ChiaYiCounty": "12460.25",
    "Pingtung": "18065.17",
    "Taitung": "8705.01",
    "Hualien": "9588.03",
    "Penghu": "5391.59",
    "Keelung": "7676.2",
    "HsinchuCity": "5022.32",
    "ChiaYiCity": "5421.24",
    "Kinmen": "3030.39",
    "Matsu": "2462.05"
}
    "Matsu": "2462.046"
}