{
    "Name": "事業廢水罰鍰金額",
    "Unit": "千元",
    "Explain": "指環保單位執行污染(包括畜牧廢水、其他事業廢水)稽查，對違反法令規定之受查對象，給予處分罰金之總額。",
    "ByYear": 95,
    "Total": "-",
    "Taiwan": "269621",
    "NewTaipei": "23272",
    "Taipei": "1870",
    "Taoyuan": "90896",
    "Taichung": "18620",
    "Tainan": "23250",
    "Kaohsiung": "34503",
    "Ilan": "6860",
    "HsinchuCounty": "8800",
    "Miaoli": "6920",
    "Changhwa": "21620",
    "Nantou": "2710",
    "Yunlin": "9870",
    "ChiaYiCounty": "3110",
    "Pingtung": "5940",
    "Taitung": "750",
    "Hualien": "4320",
    "Penghu": "640",
    "Keelung": "480",
    "HsinchuCity": "4290",
    "ChiaYiCity": "900",
    "Kinmen": "-",
    "Matsu": "-"
}"
}