{
    "1998": {
        "Name": "災害救助金額",
        "Unit": "元",
        "Explain": "因人民遭受水、火、風、雹、旱、地震及其他災害，致損害重大，影響生活者，予以災害救助；包括災害所造成人口傷亡、財物受損影響生計及住屋毀損，政府所發放之災害救助金額。",
        "ByYear": 87,
        "Total": "212540621",
        "Taiwan": "208997621",
        "NewTaipei": "20165000",
        "Taipei": "54931571",
        "Taoyuan": "4985500",
        "Taichung": "12180000",
        "Tainan": "11125000",
        "Kaohsiung": "11365000",
        "Ilan": "3132000",
        "HsinchuCounty": "1635000",
        "Miaoli": "1105000",
        "Changhwa": "1130000",
        "Nantou": "4707300",
        "Yunlin": "560000",
        "ChiaYiCounty": "12622500",
        "Pingtung": "2268750",
        "Taitung": "965000",
        "Hualien": "14458000",
        "Penghu": "-",
        "Keelung": "44910000",
        "HsinchuCity": "2760000",
        "ChiaYiCity": "3992000",
        "Kinmen": "3528000",
        "Matsu": "15000"
    },
    "1999": {
        "Name": "災害救助金額",
        "Unit": "元",
        "Explain": "因人民遭受水、火、風、雹、旱、地震及其他災害，致損害重大，影響生活者，予以災害救助；包括災害所造成人口傷亡、財物受損影響生計及住屋毀損，政府所發放之災害救助金額。",
        "ByYear": 88,
        "Total": "29963121848",
        "Taiwan": "29956011848",
        "NewTaipei": "279583000",
        "Taipei": "178732000",
        "Taoyuan": "5505000",
        "Taichung": "12781982000",
        "Tainan": "9825000",
        "Kaohsiung": "13485000",
        "Ilan": "12157000",
        "HsinchuCounty": "6427000",
        "Miaoli": "332304000",
        "Changhwa": "446787000",
        "Nantou": "15468770000",
        "Yunlin": "243530000",
        "ChiaYiCounty": "151091000",
        "Pingtung": "3355000",
        "Taitung": "1285000",
        "Hualien": "4970000",
        "Penghu": "200000",
        "Keelung": "4177308",
        "HsinchuCity": "3310000",
        "ChiaYiCity": "8536540",
        "Kinmen": "6932000",
        "Matsu": "178000"
    },
    "2000": {
        "Name": "災害救助金額",
        "Unit": "元",
        "Explain": "因人民遭受水、火、風、雹、旱、地震及其他災害，致損害重大，影響生活者，予以災害救助；包括災害所造成人口傷亡、財物受損影響生計及住屋毀損，政府所發放之災害救助金額。",
        "ByYear": 89,
        "Total": "629455638",
        "Taiwan": "629425638",
        "NewTaipei": "232470000",
        "Taipei": "84255500",
        "Taoyuan": "5504330",
        "Taichung": "12385000",
        "Tainan": "6287500",
        "Kaohsiung": "10795000",
        "Ilan": "8408598",
        "HsinchuCounty": "1625000",
        "Miaoli": "1430000",
        "Changhwa": "4235960",
        "Nantou": "18974400",
        "Yunlin": "1000000",
        "ChiaYiCounty": "2577500",
        "Pingtung": "520000",
        "Taitung": "15340000",
        "Hualien": "42491850",
        "Penghu": "-",
        "Keelung": "177465000",
        "HsinchuCity": "390000",
        "ChiaYiCity": "3270000",
        "Kinmen": "-",
        "Matsu": "30000"
    },
    "2001": {
        "Name": "災害救助金額",
        "Unit": "元",
        "Explain": "因人民遭受水、火、風、雹、旱、地震及其他災害，致損害重大，影響生活者，予以災害救助；包括災害所造成人口傷亡、財物受損影響生計及住屋毀損，政府所發放之災害救助金額。",
        "ByYear": 90,
        "Total": "968864488",
        "Taiwan": "968554488",
        "NewTaipei": "4940000",
        "Taipei": "503241250",
        "Taoyuan": "20014031",
        "Taichung": "32170000",
        "Tainan": "52096000",
        "Kaohsiung": "11363200",
        "Ilan": "36157500",
        "HsinchuCounty": "2030000",
        "Miaoli": "11053000",
        "Changhwa": "2715000",
        "Nantou": "62614877",
        "Yunlin": "1060000",
        "ChiaYiCounty": "7530000",
        "Pingtung": "1943750",
        "Taitung": "1045000",
        "Hualien": "49875880",
        "Penghu": "7030000",
        "Keelung": "152715000",
        "HsinchuCity": "1625000",
        "ChiaYiCity": "7335000",
        "Kinmen": "-",
        "Matsu": "310000"
    },
    "2002": {
        "Name": "災害救助金額",
        "Unit": "元",
        "Explain": "因人民遭受水、火、風、雹、旱、地震及其他災害，致損害重大，影響生活者，予以災害救助；包括災害所造成人口傷亡、財物受損影響生計及住屋毀損，政府所發放之災害救助金額。",
        "ByYear": 91,
        "Total": "178999352",
        "Taiwan": "178664352",
        "NewTaipei": "6130000",
        "Taipei": "23805000",
        "Taoyuan": "79405000",
        "Taichung": "4912352",
        "Tainan": "6380000",
        "Kaohsiung": "11175000",
        "Ilan": "1092000",
        "HsinchuCounty": "2885000",
        "Miaoli": "1800000",
        "Changhwa": "3190000",
        "Nantou": "3920000",
        "Yunlin": "1110000",
        "ChiaYiCounty": "3890000",
        "Pingtung": "1965000",
        "Taitung": "855000",
        "Hualien": "2820000",
        "Penghu": "240000",
        "Keelung": "20215000",
        "HsinchuCity": "745000",
        "ChiaYiCity": "2130000",
        "Kinmen": "200000",
        "Matsu": "135000"
    },
    "2003": {
        "Name": "災害救助金額",
        "Unit": "元",
        "Explain": "因人民遭受水、火、風、雹、旱、地震及其他災害，致損害重大，影響生活者，予以災害救助；包括災害所造成人口傷亡、財物受損影響生計及住屋毀損，政府所發放之災害救助金額。",
        "ByYear": 92,
        "Total": "81288200",
        "Taiwan": "80578200",
        "NewTaipei": "5960000",
        "Taipei": "6560000",
        "Taoyuan": "2505000",
        "Taichung": "9240000",
        "Tainan": "4053500",
        "Kaohsiung": "7697500",
        "Ilan": "2300000",
        "HsinchuCounty": "1500000",
        "Miaoli": "2480000",
        "Changhwa": "1265000",
        "Nantou": "6527200",
        "Yunlin": "1665000",
        "ChiaYiCounty": "1620000",
        "Pingtung": "17550000",
        "Taitung": "2935000",
        "Hualien": "4105000",
        "Penghu": "295000",
        "Keelung": "905000",
        "HsinchuCity": "380000",
        "ChiaYiCity": "1035000",
        "Kinmen": "-",
        "Matsu": "710000"
    },
    "2004": {
        "Name": "災害救助金額",
        "Unit": "元",
        "Explain": "因人民遭受水、火、風、雹、旱、地震及其他災害，致損害重大，影響生活者，予以災害救助；包括災害所造成人口傷亡、財物受損影響生計及住屋毀損，政府所發放之災害救助金額。",
        "ByYear": 93,
        "Total": "662711598",
        "Taiwan": "662636598",
        "NewTaipei": "355790000",
        "Taipei": "16980000",
        "Taoyuan": "32916293",
        "Taichung": "101207000",
        "Tainan": "6170000",
        "Kaohsiung": "10575492",
        "Ilan": "5005000",
        "HsinchuCounty": "12842813",
        "Miaoli": "11450000",
        "Changhwa": "6260000",
        "Nantou": "12700000",
        "Yunlin": "1535000",
        "ChiaYiCounty": "44720000",
        "Pingtung": "2100000",
        "Taitung": "2690000",
        "Hualien": "4220000",
        "Penghu": "555000",
        "Keelung": "32265000",
        "HsinchuCity": "2040000",
        "ChiaYiCity": "615000",
        "Kinmen": "-",
        "Matsu": "75000"
    },
    "2005": {
        "Name": "災害救助金額",
        "Unit": "元",
        "Explain": "因人民遭受水、火、風、雹、旱、地震及其他災害，致損害重大，影響生活者，予以災害救助；包括災害所造成人口傷亡、財物受損影響生計及住屋毀損，政府所發放之災害救助金額。",
        "ByYear": 94,
        "Total": "547738500",
        "Taiwan": "547658500",
        "NewTaipei": "10030000",
        "Taipei": "3480000",
        "Taoyuan": "4375000",
        "Taichung": "12500000",
        "Tainan": "187140000",
        "Kaohsiung": "76352000",
        "Ilan": "3820000",
        "HsinchuCounty": "4574000",
        "Miaoli": "4160000",
        "Changhwa": "3795000",
        "Nantou": "3300000",
        "Yunlin": "78180000",
        "ChiaYiCounty": "6790000",
        "Pingtung": "120050000",
        "Taitung": "5215000",
        "Hualien": "14357500",
        "Penghu": "135000",
        "Keelung": "3320000",
        "HsinchuCity": "3740000",
        "ChiaYiCity": "2345000",
        "Kinmen": "-",
        "Matsu": "80000"
    },
    "2006": {
        "Name": "災害救助金額",
        "Unit": "元",
        "Explain": "因人民遭受水、火、風、雹、旱、地震及其他災害，致損害重大，影響生活者，予以災害救助；包括災害所造成人口傷亡、財物受損影響生計及住屋毀損，政府所發放之災害救助金額。",
        "ByYear": 95,
        "Total": "84219438",
        "Taiwan": "84003438",
        "NewTaipei": "3385000",
        "Taipei": "4040000",
        "Taoyuan": "4910000",
        "Taichung": "7830000",
        "Tainan": "4395000",
        "Kaohsiung": "9255000",
        "Ilan": "1910000",
        "HsinchuCounty": "1049000",
        "Miaoli": "1883460",
        "Changhwa": "1335000",
        "Nantou": "3080000",
        "Yunlin": "3550000",
        "ChiaYiCounty": "8155000",
        "Pingtung": "20949589",
        "Taitung": "985000",
        "Hualien": "3031389",
        "Penghu": "-",
        "Keelung": "1330000",
        "HsinchuCity": "1400000",
        "ChiaYiCity": "1530000",
        "Kinmen": "190000",
        "Matsu": "26000"
    },
    "2007": {
        "Name": "災害救助金額",
        "Unit": "元",
        "Explain": "因人民遭受水、火、風、雹、旱、地震及其他災害，致損害重大，影響生活者，予以災害救助；包括災害所造成人口傷亡、財物受損影響生計及住屋毀損，政府所發放之災害救助金額。",
        "ByYear": 96,
        "Total": "132553485",
        "Taiwan": "132473485",
        "NewTaipei": "6210000",
        "Taipei": "3020000",
        "Taoyuan": "5635000",
        "Taichung": "7120000",
        "Tainan": "7140000",
        "Kaohsiung": "15890000",
        "Ilan": "5405000",
        "HsinchuCounty": "1227500",
        "Miaoli": "2360000",
        "Changhwa": "2060000",
        "Nantou": "1630000",
        "Yunlin": "30840000",
        "ChiaYiCounty": "4225000",
        "Pingtung": "31875000",
        "Taitung": "1000000",
        "Hualien": "3530985",
        "Penghu": "-",
        "Keelung": "1410000",
        "HsinchuCity": "1260000",
        "ChiaYiCity": "635000",
        "Kinmen": "-",
        "Matsu": "80000"
    },
    "2008": {
        "Name": "災害救助金額",
        "Unit": "元",
        "Explain": "因人民遭受水、火、風、雹、旱、地震及其他災害，致損害重大，影響生活者，予以災害救助；包括災害所造成人口傷亡、財物受損影響生計及住屋毀損，政府所發放之災害救助金額。",
        "ByYear": 97,
        "Total": "188700276",
        "Taiwan": "186737536",
        "NewTaipei": "4690000",
        "Taipei": "3370000",
        "Taoyuan": "4955000",
        "Taichung": "58900000",
        "Tainan": "13970000",
        "Kaohsiung": "51292000",
        "Ilan": "16261000",
        "HsinchuCounty": "530000",
        "Miaoli": "4120000",
        "Changhwa": "2905000",
        "Nantou": "6320000",
        "Yunlin": "9474536",
        "ChiaYiCounty": "4500000",
        "Pingtung": "380000",
        "Taitung": "575000",
        "Hualien": "1630000",
        "Penghu": "185000",
        "Keelung": "610000",
        "HsinchuCity": "1300000",
        "ChiaYiCity": "770000",
        "Kinmen": "-",
        "Matsu": "1962740"
    },
    "2009": {
        "Name": "災害救助金額",
        "Unit": "元",
        "Explain": "因人民遭受水、火、風、雹、旱、地震及其他災害，致損害重大，影響生活者，予以災害救助；包括災害所造成人口傷亡、財物受損影響生計及住屋毀損，政府所發放之災害救助金額。",
        "ByYear": 98,
        "Total": "821797601",
        "Taiwan": "821737601",
        "NewTaipei": "7410000",
        "Taipei": "7820000",
        "Taoyuan": "2325000",
        "Taichung": "5470000",
        "Tainan": "359960000",
        "Kaohsiung": "234062651",
        "Ilan": "2810000",
        "HsinchuCounty": "1085000",
        "Miaoli": "2080000",
        "Changhwa": "3355000",
        "Nantou": "7540000",
        "Yunlin": "3560000",
        "ChiaYiCounty": "18640000",
        "Pingtung": "148045000",
        "Taitung": "10740000",
        "Hualien": "1944950",
        "Penghu": "-",
        "Keelung": "710000",
        "HsinchuCity": "340000",
        "ChiaYiCity": "3840000",
        "Kinmen": "-",
        "Matsu": "60000"
    },
    "2010": {
        "Name": "災害救助金額",
        "Unit": "元",
        "Explain": "因人民遭受水、火、風、雹、旱、地震及其他災害，致損害重大，影響生活者，予以災害救助；包括災害所造成人口傷亡、財物受損影響生計及住屋毀損，政府所發放之災害救助金額。",
        "ByYear": 99,
        "Total": "792256996",
        "Taiwan": "792256996",
        "NewTaipei": "7840000",
        "Taipei": "4040000",
        "Taoyuan": "2620000",
        "Taichung": "4790000",
        "Tainan": "17670000",
        "Kaohsiung": "693245000",
        "Ilan": "920000",
        "HsinchuCounty": "420000",
        "Miaoli": "440000",
        "Changhwa": "1500000",
        "Nantou": "2040000",
        "Yunlin": "1770000",
        "ChiaYiCounty": "4020000",
        "Pingtung": "45315000",
        "Taitung": "1026996",
        "Hualien": "2640000",
        "Penghu": "20000",
        "Keelung": "400000",
        "HsinchuCity": "740000",
        "ChiaYiCity": "800000",
        "Kinmen": "-",
        "Matsu": "-"
    },
    "2011": {
        "Name": "災害救助金額",
        "Unit": "元",
        "Explain": "因人民遭受水、火、風、雹、旱、地震及其他災害，致損害重大，影響生活者，予以災害救助；包括災害所造成人口傷亡、財物受損影響生計及住屋毀損，政府所發放之災害救助金額。",
        "ByYear": 100,
        "Total": "46722902",
        "Taiwan": "46722902",
        "NewTaipei": "10840000",
        "Taipei": "3780000",
        "Taoyuan": "3435000",
        "Taichung": "7646120",
        "Tainan": "2030000",
        "Kaohsiung": "3880912",
        "Ilan": "1400000",
        "HsinchuCounty": "300870",
        "Miaoli": "1720000",
        "Changhwa": "1160000",
        "Nantou": "840000",
        "Yunlin": "660000",
        "ChiaYiCounty": "1260000",
        "Pingtung": "3650000",
        "Taitung": "895000",
        "Hualien": "1485000",
        "Penghu": "-",
        "Keelung": "745000",
        "HsinchuCity": "400000",
        "ChiaYiCity": "595000",
        "Kinmen": "-",
        "Matsu": "-"
    },
    "2012": {
        "Name": "災害救助金額",
        "Unit": "元",
        "Explain": "因人民遭受水、火、風、雹、旱、地震及其他災害，致損害重大，影響生活者，予以災害救助；包括災害所造成人口傷亡、財物受損影響生計及住屋毀損，政府所發放之災害救助金額。",
        "ByYear": 101,
        "Total": "173625676",
        "Taiwan": "173625676",
        "NewTaipei": "14820000",
        "Taipei": "7163356",
        "Taoyuan": "56093640",
        "Taichung": "8690000",
        "Tainan": "7215000",
        "Kaohsiung": "4212505",
        "Ilan": "1140000",
        "HsinchuCounty": "1175000",
        "Miaoli": "1460000",
        "Changhwa": "1767485",
        "Nantou": "2320000",
        "Yunlin": "1810000",
        "ChiaYiCounty": "2285000",
        "Pingtung": "43875000",
        "Taitung": "6905000",
        "Hualien": "4035000",
        "Penghu": "115000",
        "Keelung": "1253690",
        "HsinchuCity": "4810000",
        "ChiaYiCity": "2480000",
        "Kinmen": "-",
        "Matsu": "-"
    },
    "2013": {
        "Name": "災害救助金額",
        "Unit": "元",
        "Explain": "因人民遭受水、火、風、雹、旱、地震及其他災害，致損害重大，影響生活者，予以災害救助；包括災害所造成人口傷亡、財物受損影響生計及住屋毀損，政府所發放之災害救助金額。",
        "ByYear": 102,
        "Total": "88534273",
        "Taiwan": "88113273",
        "NewTaipei": "4760000",
        "Taipei": "6511700",
        "Taoyuan": "4585000",
        "Taichung": "11321481",
        "Tainan": "7960821",
        "Kaohsiung": "13895000",
        "Ilan": "500000",
        "HsinchuCounty": "1245000",
        "Miaoli": "3510000",
        "Changhwa": "7055000",
        "Nantou": "3180000",
        "Yunlin": "5545000",
        "ChiaYiCounty": "9755000",
        "Pingtung": "1350000",
        "Taitung": "1460000",
        "Hualien": "220000",
        "Penghu": "160000",
        "Keelung": "2894271",
        "HsinchuCity": "1300000",
        "ChiaYiCity": "905000",
        "Kinmen": "257000",
        "Matsu": "164000"
    },
    "2014": {
        "Name": "災害救助金額",
        "Unit": "元",
        "Explain": "因人民遭受水、火、風、雹、旱、地震及其他災害，致損害重大，影響生活者，予以災害救助；包括災害所造成人口傷亡、財物受損影響生計及住屋毀損，政府所發放之災害救助金額。",
        "ByYear": 103,
        "Total": "48160640",
        "Taiwan": "48137640",
        "NewTaipei": "6000000",
        "Taipei": "4060000",
        "Taoyuan": "560000",
        "Taichung": "5337640",
        "Tainan": "3050000",
        "Kaohsiung": "7190000",
        "Ilan": "1630000",
        "HsinchuCounty": "525000",
        "Miaoli": "1650000",
        "Changhwa": "6320000",
        "Nantou": "2260000",
        "Yunlin": "740000",
        "ChiaYiCounty": "1340000",
        "Pingtung": "1020000",
        "Taitung": "1775000",
        "Hualien": "1420000",
        "Penghu": "60000",
        "Keelung": "210000",
        "HsinchuCity": "1620000",
        "ChiaYiCity": "1370000",
        "Kinmen": "-",
        "Matsu": "23000"
    },
    "2015": {
        "Name": "災害救助金額",
        "Unit": "元",
        "Explain": "因人民遭受水、火、風、雹、旱、地震及其他災害，致損害重大，影響生活者，予以災害救助；包括災害所造成人口傷亡、財物受損影響生計及住屋毀損，政府所發放之災害救助金額。",
        "ByYear": 104,
        "Total": "73374761",
        "Taiwan": "73043761",
        "NewTaipei": "21870000",
        "Taipei": "5020000",
        "Taoyuan": "5420000",
        "Taichung": "4709500",
        "Tainan": "5263622",
        "Kaohsiung": "2840000",
        "Ilan": "940000",
        "HsinchuCounty": "285000",
        "Miaoli": "4100000",
        "Changhwa": "7780000",
        "Nantou": "1720000",
        "Yunlin": "1470000",
        "ChiaYiCounty": "4220000",
        "Pingtung": "1080000",
        "Taitung": "935000",
        "Hualien": "1580000",
        "Penghu": "-",
        "Keelung": "970639",
        "HsinchuCity": "2080000",
        "ChiaYiCity": "760000",
        "Kinmen": "260000",
        "Matsu": "71000"
    },
    "2016": {
        "Name": "災害救助金額",
        "Unit": "元",
        "Explain": "因人民遭受水、火、風、雹、旱、地震及其他災害，致損害重大，影響生活者，予以災害救助；包括災害所造成人口傷亡、財物受損影響生計及住屋毀損，政府所發放之災害救助金額。",
        "ByYear": 105,
        "Total": "143700075",
        "Taiwan": "142805075",
        "NewTaipei": "10060000",
        "Taipei": "4460000",
        "Taoyuan": "3140000",
        "Taichung": "11938870",
        "Tainan": "50220805",
        "Kaohsiung": "13345000",
        "Ilan": "2000000",
        "HsinchuCounty": "610000",
        "Miaoli": "4760000",
        "Changhwa": "6825000",
        "Nantou": "1820000",
        "Yunlin": "1845000",
        "ChiaYiCounty": "4400000",
        "Pingtung": "20065000",
        "Taitung": "2835000",
        "Hualien": "1755000",
        "Penghu": "-",
        "Keelung": "1185400",
        "HsinchuCity": "1300000",
        "ChiaYiCity": "240000",
        "Kinmen": "835000",
        "Matsu": "60000"
    },
    "2017": {
        "Name": "災害救助金額",
        "Unit": "元",
        "Explain": "因人民遭受水、火、風、雹、旱、地震及其他災害，致損害重大，影響生活者，予以災害救助；包括災害所造成人口傷亡、財物受損影響生計及住屋毀損，政府所發放之災害救助金額。",
        "ByYear": 106,
        "Total": "61704610",
        "Taiwan": "61694610",
        "NewTaipei": "8170000",
        "Taipei": "7140000",
        "Taoyuan": "2560000",
        "Taichung": "7625150",
        "Tainan": "3120000",
        "Kaohsiung": "3250000",
        "Ilan": "1920000",
        "HsinchuCounty": "50000",
        "Miaoli": "1280000",
        "Changhwa": "2375000",
        "Nantou": "2760000",
        "Yunlin": "2970000",
        "ChiaYiCounty": "1160000",
        "Pingtung": "9400000",
        "Taitung": "635000",
        "Hualien": "1320000",
        "Penghu": "-",
        "Keelung": "4839460",
        "HsinchuCity": "300000",
        "ChiaYiCity": "820000",
        "Kinmen": "-",
        "Matsu": "10000"
    },
    "2018": {
        "Name": "災害救助金額",
        "Unit": "元",
        "Explain": "因人民遭受水、火、風、雹、旱、地震及其他災害，致損害重大，影響生活者，予以災害救助；包括災害所造成人口傷亡、財物受損影響生計及住屋毀損，政府所發放之災害救助金額。",
        "ByYear": 107,
        "Total": "115752466",
        "Taiwan": "115489466",
        "NewTaipei": "5340000",
        "Taipei": "4450000",
        "Taoyuan": "2720000",
        "Taichung": "4060466",
        "Tainan": "27545000",
        "Kaohsiung": "23570000",
        "Ilan": "1280000",
        "HsinchuCounty": "160000",
        "Miaoli": "1300000",
        "Changhwa": "2970000",
        "Nantou": "1260000",
        "Yunlin": "4340000",
        "ChiaYiCounty": "1460000",
        "Pingtung": "1775000",
        "Taitung": "380000",
        "Hualien": "29100000",
        "Penghu": "-",
        "Keelung": "1270000",
        "HsinchuCity": "849000",
        "ChiaYiCity": "1660000",
        "Kinmen": "75000",
        "Matsu": "188000"
    },
    "2019": {
        "Name": "災害救助金額",
        "Unit": "元",
        "Explain": "因人民遭受水、火、風、雹、旱、地震及其他災害，致損害重大，影響生活者，予以災害救助；包括災害所造成人口傷亡、財物受損影響生計及住屋毀損，政府所發放之災害救助金額。",
        "ByYear": 108,
        "Total": "49591708",
        "Taiwan": "49591708",
        "NewTaipei": "3090000",
        "Taipei": "3573708",
        "Taoyuan": "2760000",
        "Taichung": "4709600",
        "Tainan": "5385000",
        "Kaohsiung": "9845000",
        "Ilan": "3293400",
        "HsinchuCounty": "1660000",
        "Miaoli": "980000",
        "Changhwa": "1610000",
        "Nantou": "1280000",
        "Yunlin": "320000",
        "ChiaYiCounty": "360000",
        "Pingtung": "2860000",
        "Taitung": "270000",
        "Hualien": "760000",
        "Penghu": "-",
        "Keelung": "680000",
        "HsinchuCity": "4755000",
        "ChiaYiCity": "1400000",
        "Kinmen": "-",
        "Matsu": "-"
    },
    "2020": {
        "Name": "災害救助金額",
        "Unit": "元",
        "Explain": "因人民遭受水、火、風、雹、旱、地震及其他災害，致損害重大，影響生活者，予以災害救助；包括災害所造成人口傷亡、財物受損影響生計及住屋毀損，政府所發放之災害救助金額。",
        "ByYear": 109,
        "Total": "34773436",
        "Taiwan": "34663436",
        "NewTaipei": "3260000",
        "Taipei": "4850000",
        "Taoyuan": "2620000",
        "Taichung": "5145600",
        "Tainan": "2505000",
        "Kaohsiung": "4315000",
        "Ilan": "1080000",
        "HsinchuCounty": "420000",
        "Miaoli": "1120000",
        "Changhwa": "1480000",
        "Nantou": "1020000",
        "Yunlin": "1620000",
        "ChiaYiCounty": "1280000",
        "Pingtung": "930000",
        "Taitung": "805000",
        "Hualien": "680000",
        "Penghu": "-",
        "Keelung": "770000",
        "HsinchuCity": "380000",
        "ChiaYiCity": "382836",
        "Kinmen": "-",
        "Matsu": "110000"
    },
    "2021": {
        "Name": "災害救助金額",
        "Unit": "元",
        "Explain": "因人民遭受水、火、風、雹、旱、地震及其他災害，致損害重大，影響生活者，予以災害救助；包括災害所造成人口傷亡、財物受損影響生計及住屋毀損，政府所發放之災害救助金額。",
        "ByYear": 110,
        "Total": "39342492",
        "Taiwan": "39268492",
        "NewTaipei": "5500000",
        "Taipei": "3800000",
        "Taoyuan": "4250000",
        "Taichung": "5647600",
        "Tainan": "1525000",
        "Kaohsiung": "4945000",
        "Ilan": "1920000",
        "HsinchuCounty": "280000",
        "Miaoli": "1940000",
        "Changhwa": "870000",
        "Nantou": "1040000",
        "Yunlin": "1170000",
        "ChiaYiCounty": "1660000",
        "Pingtung": "1635000",
        "Taitung": "250000",
        "Hualien": "790892",
        "Penghu": "-",
        "Keelung": "1305000",
        "HsinchuCity": "520000",
        "ChiaYiCity": "220000",
        "Kinmen": "-",
        "Matsu": "74000"
    },
    "2022": {
        "Name": "災害救助金額",
        "Unit": "元",
        "Explain": "因人民遭受水、火、風、雹、旱、地震及其他災害，致損害重大，影響生活者，予以災害救助；包括災害所造成人口傷亡、財物受損影響生計及住屋毀損，政府所發放之災害救助金額。",
        "ByYear": 111,
        "Total": "36987800",
        "Taiwan": "36837800",
        "NewTaipei": "4800000",
        "Taipei": "820000",
        "Taoyuan": "4240000",
        "Taichung": "4675800",
        "Tainan": "1460000",
        "Kaohsiung": "3710000",
        "Ilan": "1180000",
        "HsinchuCounty": "300000",
        "Miaoli": "1380000",
        "Changhwa": "2825000",
        "Nantou": "900000",
        "Yunlin": "960000",
        "ChiaYiCounty": "1920000",
        "Pingtung": "1200000",
        "Taitung": "490000",
        "Hualien": "2482000",
        "Penghu": "200000",
        "Keelung": "845000",
        "HsinchuCity": "2040000",
        "ChiaYiCity": "410000",
        "Kinmen": "150000",
        "Matsu": "-"
    },
    "2023": {
        "Name": "災害救助金額",
        "Unit": "元",
        "Explain": "因人民遭受水、火、風、雹、旱、地震及其他災害，致損害重大，影響生活者，予以災害救助；包括災害所造成人口傷亡、財物受損影響生計及住屋毀損，政府所發放之災害救助金額。",
        "ByYear": 112,
        "Total": "69915483",
        "Taiwan": "69855483",
        "NewTaipei": "4130000",
        "Taipei": "3140000",
        "Taoyuan": "3940000",
        "Taichung": "8465800",
        "Tainan": "1690000",
        "Kaohsiung": "2470000",
        "Ilan": "2180000",
        "HsinchuCounty": "12558900",
        "Miaoli": "1580000",
        "Changhwa": "2160000",
        "Nantou": "4661000",
        "Yunlin": "1845000",
        "ChiaYiCounty": "1600000",
        "Pingtung": "815000",
        "Taitung": "14001000",
        "Hualien": "2332783",
        "Penghu": "160000",
        "Keelung": "916000",
        "HsinchuCity": "440000",
        "ChiaYiCity": "770000",
        "Kinmen": "60000",
        "Matsu": "-"
    }
}