{"100":{"Name":"戶政管理件數","Unit":"件","Explain":"依據「戶籍法」及「戶籍法施行細則」之規定執行案件中，戶政管理件數，計分：1. 虛報遷入(出)登記。2.無戶籍人口。3. 重複戶籍。4.未接受戶籍校正。5.發現不法取得、冒用、變造國民身分證。6.受理公文件數。\n\n","ByYear":100,"Total":"12658","Taiwan":"12548","NewTaipei":"2987","Taipei":"2106","Taoyuan":"962","Taichung":"1598","Tainan":"655","Kaohsiung":"859","Ilan":"210","HsinchuCounty":"300","Miaoli":"187","Changhwa":"681","Nantou":"100","Yunlin":"371","ChiaYiCounty":"279","Pingtung":"339","Taitung":"143","Hualien":"168","Penghu":"29","Keelung":"264","HsinchuCity":"124","ChiaYiCity":"186","Kinmen":"102","Matsu":"8"},"101":{"Name":"戶政管理件數","Unit":"件","Explain":"依據「戶籍法」及「戶籍法施行細則」之規定執行案件中，戶政管理件數，計分：1. 虛報遷入(出)登記。2.無戶籍人口。3. 重複戶籍。4.未接受戶籍校正。5.發現不法取得、冒用、變造國民身分證。6.受理公文件數。\n\n","ByYear":101,"Total":"10983","Taiwan":"10848","NewTaipei":"2713","Taipei":"1786","Taoyuan":"1063","Taichung":"1055","Tainan":"446","Kaohsiung":"739","Ilan":"179","HsinchuCounty":"236","Miaoli":"232","Changhwa":"619","Nantou":"113","Yunlin":"331","ChiaYiCounty":"220","Pingtung":"332","Taitung":"143","Hualien":"134","Penghu":"13","Keelung":"224","HsinchuCity":"100","ChiaYiCity":"170","Kinmen":"123","Matsu":"12"},"102":{"Name":"戶政管理件數","Unit":"件","Explain":"依據「戶籍法」及「戶籍法施行細則」之規定執行案件中，戶政管理件數，計分：1. 虛報遷入(出)登記。2.無戶籍人口。3. 重複戶籍。4.未接受戶籍校正。5.發現不法取得、冒用、變造國民身分證。6.受理公文件數。\n\n","ByYear":102,"Total":"9794","Taiwan":"9611","NewTaipei":"2246","Taipei":"1584","Taoyuan":"780","Taichung":"1089","Tainan":"403","Kaohsiung":"704","Ilan":"162","HsinchuCounty":"285","Miaoli":"166","Changhwa":"542","Nantou":"62","Yunlin":"306","ChiaYiCounty":"171","Pingtung":"286","Taitung":"121","Hualien":"140","Penghu":"14","Keelung":"314","HsinchuCity":"99","ChiaYiCity":"137","Kinmen":"168","Matsu":"15"},"103":{"Name":"戶政管理件數","Unit":"件","Explain":"依據「戶籍法」及「戶籍法施行細則」之規定執行案件中，戶政管理件數，計分：1. 虛報遷入(出)登記。2.無戶籍人口。3. 重複戶籍。4.未接受戶籍校正。5.發現不法取得、冒用、變造國民身分證。6.受理公文件數。\n\n","ByYear":103,"Total":"11182","Taiwan":"11082","NewTaipei":"2212","Taipei":"1937","Taoyuan":"821","Taichung":"1237","Tainan":"1140","Kaohsiung":"699","Ilan":"180","HsinchuCounty":"229","Miaoli":"188","Changhwa":"498","Nantou":"88","Yunlin":"315","ChiaYiCounty":"170","Pingtung":"351","Taitung":"114","Hualien":"89","Penghu":"17","Keelung":"238","HsinchuCity":"352","ChiaYiCity":"132","Kinmen":"136","Matsu":"39"},"104":{"Name":"戶政管理件數","Unit":"件","Explain":"依據「戶籍法」及「戶籍法施行細則」之規定執行案件中，戶政管理件數，計分：1. 虛報遷入(出)登記。2.無戶籍人口。3. 重複戶籍。4.未接受戶籍校正。5.發現不法取得、冒用、變造國民身分證。6.受理公文件數。\n\n","ByYear":104,"Total":"1348564","Taiwan":"1339201","NewTaipei":"181013","Taipei":"157187","Taoyuan":"106886","Taichung":"140498","Tainan":"134579","Kaohsiung":"171515","Ilan":"31926","HsinchuCounty":"25931","Miaoli":"41106","Changhwa":"59707","Nantou":"39580","Yunlin":"52117","ChiaYiCounty":"42168","Pingtung":"47789","Taitung":"10599","Hualien":"34080","Penghu":"10105","Keelung":"22965","HsinchuCity":"19929","ChiaYiCity":"9521","Kinmen":"9361","Matsu":"2"},"105":{"Name":"戶政管理件數","Unit":"件","Explain":"依據「戶籍法」及「戶籍法施行細則」之規定執行案件中，戶政管理件數，計分：1. 虛報遷入(出)登記。2.無戶籍人口。3. 重複戶籍。4.未接受戶籍校正。5.發現不法取得、冒用、變造國民身分證。6.受理公文件數。\n\n","ByYear":105,"Total":"1350936","Taiwan":"1341718","NewTaipei":"194218","Taipei":"148386","Taoyuan":"111606","Taichung":"153691","Tainan":"132400","Kaohsiung":"165438","Ilan":"30618","HsinchuCounty":"28893","Miaoli":"41960","Changhwa":"58119","Nantou":"38207","Yunlin":"50045","ChiaYiCounty":"28511","Pingtung":"47583","Taitung":"11069","Hualien":"34624","Penghu":"10709","Keelung":"24290","HsinchuCity":"19552","ChiaYiCity":"11799","Kinmen":"9218","Matsu":"-"},"106":{"Name":"戶政管理件數","Unit":"件","Explain":"依據「戶籍法」及「戶籍法施行細則」之規定執行案件中，戶政管理件數，計分：1. 虛報遷入(出)登記。2.無戶籍人口。3. 重複戶籍。4.未接受戶籍校正。5.發現不法取得、冒用、變造國民身分證。6.受理公文件數。\n\n","ByYear":106,"Total":"1265472","Taiwan":"1255068","NewTaipei":"197811","Taipei":"144654","Taoyuan":"108603","Taichung":"144242","Tainan":"105924","Kaohsiung":"159453","Ilan":"28758","HsinchuCounty":"25975","Miaoli":"41316","Changhwa":"52935","Nantou":"37238","Yunlin":"44962","ChiaYiCounty":"13981","Pingtung":"43469","Taitung":"10220","Hualien":"32413","Penghu":"10173","Keelung":"24042","HsinchuCity":"18006","ChiaYiCity":"10893","Kinmen":"9140","Matsu":"1264"},"107":{"Name":"戶政管理件數","Unit":"件","Explain":"依據「戶籍法」及「戶籍法施行細則」之規定執行案件中，戶政管理件數，計分：1. 虛報遷入(出)登記。2.無戶籍人口。3. 重複戶籍。4.未接受戶籍校正。5.發現不法取得、冒用、變造國民身分證。6.受理公文件數。\n\n","ByYear":107,"Total":"1235457","Taiwan":"1222179","NewTaipei":"200969","Taipei":"140950","Taoyuan":"113354","Taichung":"137956","Tainan":"89322","Kaohsiung":"153630","Ilan":"31325","HsinchuCounty":"29271","Miaoli":"44295","Changhwa":"43843","Nantou":"39298","Yunlin":"21797","ChiaYiCounty":"14725","Pingtung":"45492","Taitung":"11369","Hualien":"35345","Penghu":"10749","Keelung":"26556","HsinchuCity":"19946","ChiaYiCity":"11987","Kinmen":"9898","Matsu":"3380"},"108":{"Name":"戶政管理件數","Unit":"件","Explain":"依據「戶籍法」及「戶籍法施行細則」之規定執行案件中，戶政管理件數，計分：1. 虛報遷入(出)登記。2.無戶籍人口。3. 重複戶籍。4.未接受戶籍校正。5.發現不法取得、冒用、變造國民身分證。6.受理公文件數。\n\n","ByYear":108,"Total":"1191937","Taiwan":"1179973","NewTaipei":"202313","Taipei":"132120","Taoyuan":"112230","Taichung":"132587","Tainan":"81672","Kaohsiung":"155661","Ilan":"29835","HsinchuCounty":"30362","Miaoli":"38760","Changhwa":"44257","Nantou":"36043","Yunlin":"20870","ChiaYiCounty":"14214","Pingtung":"41303","Taitung":"10519","Hualien":"34689","Penghu":"9368","Keelung":"24378","HsinchuCity":"16956","ChiaYiCity":"11836","Kinmen":"9569","Matsu":"2395"},"87":{"Name":"戶政管理件數","Unit":"件","Explain":"依據「戶籍法」及「戶籍法施行細則」之規定執行案件中，戶政管理件數，計分：1. 虛報遷入(出)登記。2.無戶籍人口。3. 重複戶籍。4.未接受戶籍校正。5.發現不法取得、冒用、變造國民身分證。6.受理公文件數。\n\n","ByYear":87,"Total":"21024","Taiwan":"20972","NewTaipei":"2008","Taipei":"2342","Taoyuan":"1123","Taichung":"2561","Tainan":"2435","Kaohsiung":"2537","Ilan":"501","HsinchuCounty":"192","Miaoli":"271","Changhwa":"2258","Nantou":"396","Yunlin":"951","ChiaYiCounty":"612","Pingtung":"896","Taitung":"725","Hualien":"80","Penghu":"86","Keelung":"337","HsinchuCity":"224","ChiaYiCity":"437","Kinmen":"52","Matsu":"-"},"88":{"Name":"戶政管理件數","Unit":"件","Explain":"依據「戶籍法」及「戶籍法施行細則」之規定執行案件中，戶政管理件數，計分：1. 虛報遷入(出)登記。2.無戶籍人口。3. 重複戶籍。4.未接受戶籍校正。5.發現不法取得、冒用、變造國民身分證。6.受理公文件數。\n\n","ByYear":88,"Total":"18111","Taiwan":"18059","NewTaipei":"2263","Taipei":"2555","Taoyuan":"1249","Taichung":"2438","Tainan":"1886","Kaohsiung":"2196","Ilan":"420","HsinchuCounty":"241","Miaoli":"102","Changhwa":"1124","Nantou":"367","Yunlin":"824","ChiaYiCounty":"369","Pingtung":"708","Taitung":"278","Hualien":"43","Penghu":"43","Keelung":"462","HsinchuCity":"174","ChiaYiCity":"317","Kinmen":"52","Matsu":"-"},"89":{"Name":"戶政管理件數","Unit":"件","Explain":"依據「戶籍法」及「戶籍法施行細則」之規定執行案件中，戶政管理件數，計分：1. 虛報遷入(出)登記。2.無戶籍人口。3. 重複戶籍。4.未接受戶籍校正。5.發現不法取得、冒用、變造國民身分證。6.受理公文件數。\n\n","ByYear":89,"Total":"22175","Taiwan":"22129","NewTaipei":"2933","Taipei":"3749","Taoyuan":"1760","Taichung":"3224","Tainan":"1809","Kaohsiung":"2452","Ilan":"483","HsinchuCounty":"347","Miaoli":"131","Changhwa":"1254","Nantou":"428","Yunlin":"862","ChiaYiCounty":"528","Pingtung":"793","Taitung":"320","Hualien":"49","Penghu":"56","Keelung":"493","HsinchuCity":"141","ChiaYiCity":"317","Kinmen":"46","Matsu":"-"},"90":{"Name":"戶政管理件數","Unit":"件","Explain":"依據「戶籍法」及「戶籍法施行細則」之規定執行案件中，戶政管理件數，計分：1. 虛報遷入(出)登記。2.無戶籍人口。3. 重複戶籍。4.未接受戶籍校正。5.發現不法取得、冒用、變造國民身分證。6.受理公文件數。\n\n","ByYear":90,"Total":"24580","Taiwan":"24524","NewTaipei":"3715","Taipei":"4469","Taoyuan":"1744","Taichung":"3285","Tainan":"2057","Kaohsiung":"3590","Ilan":"428","HsinchuCounty":"299","Miaoli":"82","Changhwa":"1098","Nantou":"385","Yunlin":"737","ChiaYiCounty":"495","Pingtung":"729","Taitung":"337","Hualien":"35","Penghu":"138","Keelung":"464","HsinchuCity":"133","ChiaYiCity":"304","Kinmen":"31","Matsu":"25"},"91":{"Name":"戶政管理件數","Unit":"件","Explain":"依據「戶籍法」及「戶籍法施行細則」之規定執行案件中，戶政管理件數，計分：1. 虛報遷入(出)登記。2.無戶籍人口。3. 重複戶籍。4.未接受戶籍校正。5.發現不法取得、冒用、變造國民身分證。6.受理公文件數。\n\n","ByYear":91,"Total":"41492","Taiwan":"41331","NewTaipei":"5486","Taipei":"6664","Taoyuan":"2930","Taichung":"6397","Tainan":"3325","Kaohsiung":"5021","Ilan":"633","HsinchuCounty":"541","Miaoli":"176","Changhwa":"2354","Nantou":"813","Yunlin":"1460","ChiaYiCounty":"1228","Pingtung":"1238","Taitung":"1128","Hualien":"208","Penghu":"227","Keelung":"572","HsinchuCity":"301","ChiaYiCity":"629","Kinmen":"124","Matsu":"37"},"92":{"Name":"戶政管理件數","Unit":"件","Explain":"依據「戶籍法」及「戶籍法施行細則」之規定執行案件中，戶政管理件數，計分：1. 虛報遷入(出)登記。2.無戶籍人口。3. 重複戶籍。4.未接受戶籍校正。5.發現不法取得、冒用、變造國民身分證。6.受理公文件數。\n\n","ByYear":92,"Total":"40274","Taiwan":"40128","NewTaipei":"6182","Taipei":"6525","Taoyuan":"3136","Taichung":"6401","Tainan":"2612","Kaohsiung":"4895","Ilan":"728","HsinchuCounty":"578","Miaoli":"188","Changhwa":"2219","Nantou":"670","Yunlin":"1301","ChiaYiCounty":"908","Pingtung":"1121","Taitung":"779","Hualien":"202","Penghu":"130","Keelung":"572","HsinchuCity":"418","ChiaYiCity":"563","Kinmen":"120","Matsu":"26"},"93":{"Name":"戶政管理件數","Unit":"件","Explain":"依據「戶籍法」及「戶籍法施行細則」之規定執行案件中，戶政管理件數，計分：1. 虛報遷入(出)登記。2.無戶籍人口。3. 重複戶籍。4.未接受戶籍校正。5.發現不法取得、冒用、變造國民身分證。6.受理公文件數。\n\n","ByYear":93,"Total":"47488","Taiwan":"47292","NewTaipei":"7995","Taipei":"7971","Taoyuan":"3824","Taichung":"7547","Tainan":"2827","Kaohsiung":"5583","Ilan":"839","HsinchuCounty":"710","Miaoli":"177","Changhwa":"2554","Nantou":"826","Yunlin":"1341","ChiaYiCounty":"871","Pingtung":"1267","Taitung":"775","Hualien":"233","Penghu":"132","Keelung":"700","HsinchuCity":"501","ChiaYiCity":"619","Kinmen":"170","Matsu":"26"},"94":{"Name":"戶政管理件數","Unit":"件","Explain":"依據「戶籍法」及「戶籍法施行細則」之規定執行案件中，戶政管理件數，計分：1. 虛報遷入(出)登記。2.無戶籍人口。3. 重複戶籍。4.未接受戶籍校正。5.發現不法取得、冒用、變造國民身分證。6.受理公文件數。\n\n","ByYear":94,"Total":"58616","Taiwan":"58385","NewTaipei":"11519","Taipei":"10360","Taoyuan":"4604","Taichung":"8514","Tainan":"3406","Kaohsiung":"6468","Ilan":"904","HsinchuCounty":"1035","Miaoli":"184","Changhwa":"2750","Nantou":"901","Yunlin":"1473","ChiaYiCounty":"1070","Pingtung":"1379","Taitung":"1189","Hualien":"211","Penghu":"141","Keelung":"901","HsinchuCity":"633","ChiaYiCity":"743","Kinmen":"197","Matsu":"34"},"95":{"Name":"戶政管理件數","Unit":"件","Explain":"依據「戶籍法」及「戶籍法施行細則」之規定執行案件中，戶政管理件數，計分：1. 虛報遷入(出)登記。2.無戶籍人口。3. 重複戶籍。4.未接受戶籍校正。5.發現不法取得、冒用、變造國民身分證。6.受理公文件數。\n\n","ByYear":95,"Total":"85772","Taiwan":"85442","NewTaipei":"19456","Taipei":"15087","Taoyuan":"6334","Taichung":"11612","Tainan":"5076","Kaohsiung":"9204","Ilan":"1174","HsinchuCounty":"1588","Miaoli":"329","Changhwa":"3510","Nantou":"1223","Yunlin":"1914","ChiaYiCounty":"1364","Pingtung":"2155","Taitung":"1425","Hualien":"622","Penghu":"217","Keelung":"1253","HsinchuCity":"949","ChiaYiCity":"950","Kinmen":"289","Matsu":"41"},"96":{"Name":"戶政管理件數","Unit":"件","Explain":"依據「戶籍法」及「戶籍法施行細則」之規定執行案件中，戶政管理件數，計分：1. 虛報遷入(出)登記。2.無戶籍人口。3. 重複戶籍。4.未接受戶籍校正。5.發現不法取得、冒用、變造國民身分證。6.受理公文件數。\n\n","ByYear":96,"Total":"76962","Taiwan":"76655","NewTaipei":"17196","Taipei":"13468","Taoyuan":"5094","Taichung":"10062","Tainan":"4589","Kaohsiung":"8070","Ilan":"1194","HsinchuCounty":"2296","Miaoli":"432","Changhwa":"3073","Nantou":"1168","Yunlin":"1678","ChiaYiCounty":"1195","Pingtung":"1882","Taitung":"1092","Hualien":"750","Penghu":"136","Keelung":"1502","HsinchuCity":"842","ChiaYiCity":"936","Kinmen":"279","Matsu":"28"},"97":{"Name":"戶政管理件數","Unit":"件","Explain":"依據「戶籍法」及「戶籍法施行細則」之規定執行案件中，戶政管理件數，計分：1. 虛報遷入(出)登記。2.無戶籍人口。3. 重複戶籍。4.未接受戶籍校正。5.發現不法取得、冒用、變造國民身分證。6.受理公文件數。\n\n","ByYear":97,"Total":"52858","Taiwan":"52650","NewTaipei":"12493","Taipei":"8801","Taoyuan":"3798","Taichung":"6839","Tainan":"3491","Kaohsiung":"5585","Ilan":"753","HsinchuCounty":"1123","Miaoli":"339","Changhwa":"1987","Nantou":"741","Yunlin":"1106","ChiaYiCounty":"799","Pingtung":"1301","Taitung":"427","Hualien":"582","Penghu":"72","Keelung":"1118","HsinchuCity":"668","ChiaYiCity":"627","Kinmen":"193","Matsu":"15"},"98":{"Name":"戶政管理件數","Unit":"件","Explain":"依據「戶籍法」及「戶籍法施行細則」之規定執行案件中，戶政管理件數，計分：1. 虛報遷入(出)登記。2.無戶籍人口。3. 重複戶籍。4.未接受戶籍校正。5.發現不法取得、冒用、變造國民身分證。6.受理公文件數。\n\n","ByYear":98,"Total":"25068","Taiwan":"24906","NewTaipei":"5645","Taipei":"3677","Taoyuan":"1988","Taichung":"3299","Tainan":"1817","Kaohsiung":"2995","Ilan":"301","HsinchuCounty":"560","Miaoli":"194","Changhwa":"807","Nantou":"289","Yunlin":"481","ChiaYiCounty":"384","Pingtung":"670","Taitung":"199","Hualien":"328","Penghu":"36","Keelung":"576","HsinchuCity":"278","ChiaYiCity":"382","Kinmen":"141","Matsu":"21"},"99":{"Name":"戶政管理件數","Unit":"件","Explain":"依據「戶籍法」及「戶籍法施行細則」之規定執行案件中，戶政管理件數，計分：1. 虛報遷入(出)登記。2.無戶籍人口。3. 重複戶籍。4.未接受戶籍校正。5.發現不法取得、冒用、變造國民身分證。6.受理公文件數。\n\n","ByYear":99,"Total":"17185","Taiwan":"17062","NewTaipei":"3402","Taipei":"2629","Taoyuan":"1409","Taichung":"2242","Tainan":"1132","Kaohsiung":"1810","Ilan":"241","HsinchuCounty":"396","Miaoli":"241","Changhwa":"851","Nantou":"194","Yunlin":"436","ChiaYiCounty":"310","Pingtung":"456","Taitung":"178","Hualien":"216","Penghu":"27","Keelung":"411","HsinchuCity":"167","ChiaYiCity":"314","Kinmen":"117","Matsu":"6"}}