{
    "Name": "領有汽車駕照人數",
    "Unit": "人",
    "Explain": "指由駕駛人向公路監理機關申請登記，考驗及格後發給駕駛汽車之許可憑證。",
    "ByYear": 112,
    "Total": "14674271",
    "Taiwan": "14599803",
    "NewTaipei": "2326343",
    "Taipei": "1624410",
    "Taoyuan": "1435004",
    "Taichung": "1931303",
    "Tainan": "1203339",
    "Kaohsiung": "1747125",
    "Ilan": "275461",
    "HsinchuCounty": "364741",
    "Miaoli": "338027",
    "Changhwa": "787785",
    "Nantou": "306955",
    "Yunlin": "417086",
    "ChiaYiCounty": "312916",
    "Pingtung": "491649",
    "Taitung": "121174",
    "Hualien": "198816",
    "Penghu": "50398",
    "Keelung": "209029",
    "HsinchuCity": "292618",
    "ChiaYiCity": "165624",
    "Kinmen": "68883",
    "Matsu": "5585"
}