{
    "Name": "平均每班學生數-國小",
    "Unit": "人",
    "Explain": "國小平均每班學生數。",
    "ByYear": 101,
    "Total": "24.35",
    "Taiwan": "24.38",
    "NewTaipei": "26.66",
    "Taipei": "24.89",
    "Taoyuan": "26.65",
    "Taichung": "25.85",
    "Tainan": "24.24",
    "Kaohsiung": "25.21",
    "Ilan": "21.14",
    "HsinchuCounty": "24.4",
    "Miaoli": "20.78",
    "Changhwa": "24.88",
    "Nantou": "19.15",
    "Yunlin": "21.8",
    "ChiaYiCounty": "19.4",
    "Pingtung": "21.32",
    "Taitung": "15.87",
    "Hualien": "18.27",
    "Penghu": "14.28",
    "Keelung": "24.19",
    "HsinchuCity": "26.71",
    "ChiaYiCity": "27.33",
    "Kinmen": "20.16",
    "Matsu": "9.06"
}