{"Name":"電燈用戶數","Unit":"戶","Explain":"係指台電公司包燈用電與表燈用電（含營業用、非營業用）之用戶數。","ByYear":104,"Total":"13298978","Taiwan":"13266039","NewTaipei":"1957828","Taipei":"1163710","Taoyuan":"1143117","Taichung":"1599392","Tainan":"1219318","Kaohsiung":"1699605","Ilan":"288244","HsinchuCounty":"304984","Miaoli":"334041","Changhwa":"823147","Nantou":"302412","Yunlin":"541182","ChiaYiCounty":"357765","Pingtung":"557671","Taitung":"128038","Hualien":"191203","Penghu":"48163","Keelung":"194815","HsinchuCity":"244170","ChiaYiCity":"167234","Kinmen":"28119","Matsu":"4820"}167234","金門縣":"28119","連江縣":"4820"}