{
    "Name": "82歲人口數",
    "Unit": "人",
    "Explain": "於統計標準日戶籍登記實足年齡為82歲人口數。",
    "ByYear": 103,
    "Total": "75667",
    "Taiwan": "75222",
    "NewTaipei": "9115",
    "Taipei": "10214",
    "Taoyuan": "5101",
    "Taichung": "6915",
    "Tainan": "6786",
    "Kaohsiung": "8040",
    "Ilan": "1805",
    "HsinchuCounty": "1784",
    "Miaoli": "2507",
    "Changhwa": "5344",
    "Nantou": "2304",
    "Yunlin": "3487",
    "ChiaYiCounty": "2740",
    "Pingtung": "3171",
    "Taitung": "847",
    "Hualien": "1195",
    "Penghu": "542",
    "Keelung": "1208",
    "HsinchuCity": "1204",
    "ChiaYiCity": "913",
    "Kinmen": "418",
    "Matsu": "27"
}