{"Name":"é“è·¯äº¤é€šäº‹æ•…è‚‡äº‹ç¸½ä»¶æ•¸(A1+A2é¡)","Unit":"ä»¶","Explain":"è­¦å¯Ÿæ©Ÿé—œçµ±è¨ˆé“è·¯äº¤é€šäº‹æ•…ä»¶æ•¸ï¼›å…«åå…«å¹´ä»¥å‰åƒ…åŒ…å«A1é¡ã€‚","ByYear":90,"Total":"64264","Taiwan":"64077","NewTaipei":"3059","Taipei":"12604","Taoyuan":"2624","Taichung":"10432","Tainan":"6098","Kaohsiung":"8215","Ilan":"887","HsinchuCounty":"931","Miaoli":"1304","ChangHwa":"1942","Nantou":"883","Yunlin":"2482","ChiaYiCounty":"1101","Pingtung":"2747","Taitung":"1521","Hualien":"1254","Penghu":"233","Keelung":"1103","HsinchuCity":"1707","ChiaYiCity":"2173","Kinmen":"185","Matsu":"2"}©å¸‚":"2173","é‡‘é–€ç¸£":"185","é€£æ±Ÿç¸£":"2"}