{"Name":"老人長期照顧、安養機構可供進住人數占老年人口比率","Unit":"人／萬人","Explain":"每萬名老人中，可由長期照顧、安養機構收容之人數。","ByYear":108,"Total":"173.69","Taiwan":"159.07","NewTaipei":"181.29","Taipei":"114.55","Taoyuan":"124.44","Taichung":"113.02","Tainan":"188.24","Kaohsiung":"181.41","Ilan":"322.2","HsinchuCounty":"177.76","Miaoli":"98.14","Changhwa":"139.21","Nantou":"140.85","Yunlin":"159.64","ChiaYiCounty":"133.02","Pingtung":"212.66","Taitung":"222.71","Hualien":"188.52","Penghu":"77.18","Keelung":"312.73","HsinchuCity":"68.78","ChiaYiCity":"203.1","Kinmen":"141.52","Matsu":"215.74"}3.1","金門縣":"141.52","連江縣":"215.74"}