{"Name":"12歲人口數","Unit":"人","Explain":"於統計標準日戶籍登記實足年齡為12歲人口數。","ByYear":99,"Total":"267446","Taiwan":"266688","NewTaipei":"42524","Taipei":"28506","Taoyuan":"26632","Taichung":"34015","Tainan":"20355","Kaohsiung":"30479","Ilan":"5458","HsinchuCounty":"6399","Miaoli":"6121","ChangHwa":"15549","Nantou":"6022","Yunlin":"8202","ChiaYiCounty":"5595","Pingtung":"9836","Taitung":"2657","Hualien":"3884","Penghu":"937","Keelung":"4417","HsinchuCity":"5214","ChiaYiCity":"3886","Kinmen":"675","Matsu":"83"}市":"3886","金門縣":"675","連江縣":"83"}