{"Name":"åœ‹å°ç­ç´šæ•¸","Unit":"ç­","Explain":"å„å…¬ç§ç«‹åœ‹æ°‘å°å­¸ç­ç´šæ•¸ã€‚","ByYear":108,"Total":"51119","Taiwan":"50871","NewTaipei":"7795","Taipei":"4608","Taoyuan":"5114","Taichung":"6354","Tainan":"3977","Kaohsiung":"5353","Ilan":"1089","HsinchuCounty":"1619","Miaoli":"1462","ChangHwa":"2777","Nantou":"1371","Yunlin":"1688","ChiaYiCounty":"1226","Pingtung":"1870","Taitung":"755","Hualien":"966","Penghu":"291","Keelung":"708","HsinchuCity":"1239","ChiaYiCity":"609","Kinmen":"204","Matsu":"44"}©å¸‚":"609","é‡‘é–€ç¸£":"204","é€£æ±Ÿç¸£":"44"}