{
    "Name": "空氣中臭氧濃度",
    "Unit": "ppb",
    "Explain": "臭氧為光化學霧之主要成份，具強氧化力，對人體黏膜有刺激作用，並對植物會造成重大傷害。各地區濃度為該地區各一般自動監測站濃度之各日最大有效小時值之算術平均值。",
    "ByYear": 93,
    "Total": "-",
    "Taiwan": "61.47",
    "NewTaipei": "57.1",
    "Taipei": "54.62",
    "Taoyuan": "50.43",
    "Taichung": "64.64",
    "Tainan": "72.05",
    "Kaohsiung": "71.58",
    "Ilan": "47.6",
    "HsinchuCounty": "57.1",
    "Miaoli": "62.45",
    "Changhwa": "60.35",
    "Nantou": "79.45",
    "Yunlin": "68.5",
    "ChiaYiCounty": "65.3",
    "Pingtung": "64.63",
    "Taitung": "38.3",
    "Hualien": "39.8",
    "Penghu": "-",
    "Keelung": "53.6",
    "HsinchuCity": "53.2",
    "ChiaYiCity": "70.8",
    "Kinmen": "-",
    "Matsu": "-"
}