{"Name":"55æ­²äººå£æ•¸","Unit":"äºº","Explain":"æ–¼çµ±è¨ˆæ¨™æº–æ—¥æˆ¶ç±ç™»è¨˜å¯¦è¶³å¹´é½¡ç‚º55æ­²äººå£æ•¸ã€‚","ByYear":105,"Total":"366236","Taiwan":"363722","NewTaipei":"64564","Taipei":"40171","Taoyuan":"30674","Taichung":"41115","Tainan":"31451","Kaohsiung":"43919","Ilan":"7328","HsinchuCounty":"7473","Miaoli":"8737","ChangHwa":"19439","Nantou":"8397","Yunlin":"10685","ChiaYiCounty":"8817","Pingtung":"13946","Taitung":"3544","Hualien":"5463","Penghu":"1633","Keelung":"6536","HsinchuCity":"5762","ChiaYiCity":"4068","Kinmen":"2299","Matsu":"215"}‚":"4068","é‡‘é–€ç¸£":"2299","é€£æ±Ÿç¸£":"215"}