{
    "Name": "歲出政事別-警政支出",
    "Unit": "百萬元",
    "Explain": "關於縣 (市) 警察經費及補助之支出均屬之。",
    "ByYear": 97,
    "Total": "77431.189",
    "Taiwan": "76828.593",
    "NewTaipei": "9539.475",
    "Taipei": "11791.855",
    "Taoyuan": "4958.843",
    "Taichung": "8527.072",
    "Tainan": "5837.896",
    "Kaohsiung": "9695.567",
    "Ilan": "1715.118",
    "HsinchuCounty": "1430.732",
    "Miaoli": "1923.609",
    "Changhwa": "3847.006",
    "Nantou": "2139.84",
    "Yunlin": "2168.584",
    "ChiaYiCounty": "1864.768",
    "Pingtung": "2712.239",
    "Taitung": "1471.001",
    "Hualien": "1790.222",
    "Penghu": "1116.502",
    "Keelung": "1738.88",
    "HsinchuCity": "1414.776",
    "ChiaYiCity": "1144.596",
    "Kinmen": "475.678",
    "Matsu": "126.917"
}