{
    "Name": "每萬名接受特殊境遇家庭緊急生活扶助人次",
    "Unit": "人次/萬人",
    "Explain": "97年以前項目定義：每萬名婦女當中，於一定期間內接受特殊境遇婦女緊急生活扶助之人次。98年以後項目定義：每萬名人口當中，於一定期間內接受特殊境遇家庭緊急生活扶助之人次。",
    "ByYear": 109,
    "Total": "5.92",
    "Taiwan": "5.95",
    "NewTaipei": "5.14",
    "Taipei": "9.94",
    "Taoyuan": "2.86",
    "Taichung": "7.31",
    "Tainan": "3",
    "Kaohsiung": "2.65",
    "Ilan": "0.53",
    "HsinchuCounty": "4.23",
    "Miaoli": "6.89",
    "Changhwa": "9.62",
    "Nantou": "11.94",
    "Yunlin": "8.92",
    "ChiaYiCounty": "8.38",
    "Pingtung": "7.97",
    "Taitung": "8.05",
    "Hualien": "12.45",
    "Penghu": "5.11",
    "Keelung": "1.71",
    "HsinchuCity": "5",
    "ChiaYiCity": "7.98",
    "Kinmen": "-",
    "Matsu": "6.83"
}