{"Name":"å°±æ¥­è€…å¾æ¥­èº«åˆ†çµæ§‹-ç„¡é…¬å®¶å±¬å·¥ä½œè€…","Unit":"ï¼…","Explain":"å°±æ¥­è€…ä¸»è¦å·¥ä½œå ´æ‰€ä¹‹èº«åˆ†ä¿‚åœ¨å®¶å±¬ç¶“ç‡Ÿä¹‹äº‹æ¥­å…§å¹«å¿™å·¥ä½œè€Œä¸æ”¯é ˜å›ºå®šå ±é…¬è€…å ç¸½å°±æ¥­è€…ä¹‹ç™¾åˆ†æ¯”ã€‚","ByYear":102,"Total":"...","Taiwan":"5.17","NewTaipei":"3.13","Taipei":"2.39","Taoyuan":"3.28","Taichung":"6.98","Tainan":"6.39","Kaohsiung":"4.79","Ilan":"6.98","HsinchuCounty":"3.55","Miaoli":"4.61","ChangHwa":"7.48","Nantou":"10","Yunlin":"9.38","ChiaYiCounty":"10.13","Pingtung":"7.29","Taitung":"9.5","Hualien":"5.89","Penghu":"4.15","Keelung":"3.9","HsinchuCity":"3.53","ChiaYiCity":"6.84","Kinmen":"5.35","Matsu":"1.5"}‚":"6.84","é‡‘é–€ç¸£":"5.35","é€£æ±Ÿç¸£":"1.5"}