{
    "Name": "平均每一鄉鎮市區擁有社區發展協會數",
    "Unit": "個／個",
    "Explain": "平均每一鄉鎮市區所擁有之社區發展協會個數。",
    "ByYear": 98,
    "Total": "17.508152173913",
    "Taiwan": "17.6843575418994",
    "NewTaipei": "14.551724137931",
    "Taipei": "27.75",
    "Taoyuan": "18.3076923076923",
    "Taichung": "19.7586206896552",
    "Tainan": "18.1081081081081",
    "Kaohsiung": "18.9736842105263",
    "Ilan": "19.4166666666667",
    "HsinchuCounty": "13.3846153846154",
    "Miaoli": "15.3333333333333",
    "Changhwa": "19.9615384615385",
    "Nantou": "19.6923076923077",
    "Yunlin": "20.9",
    "ChiaYiCounty": "18.7777777777778",
    "Pingtung": "13.7575757575758",
    "Taitung": "9",
    "Hualien": "12.7692307692308",
    "Penghu": "14.8333333333333",
    "Keelung": "20.2857142857143",
    "HsinchuCity": "37",
    "ChiaYiCity": "27",
    "Kinmen": "15.3333333333333",
    "Matsu": "5"
}