{
    "Name": "歲入來源別-財產收入",
    "Unit": "百萬元",
    "Explain": "包含財產之孳息、售價及資本之收回等收入。",
    "ByYear": 101,
    "Total": "24674.12",
    "Taiwan": "24551.06",
    "NewTaipei": "3541.88",
    "Taipei": "3643.01",
    "Taoyuan": "508.1",
    "Taichung": "1851.55",
    "Tainan": "5819.66",
    "Kaohsiung": "4116.18",
    "Ilan": "1554.31",
    "HsinchuCounty": "402.57",
    "Miaoli": "308.95",
    "Changhwa": "103.95",
    "Nantou": "33.85",
    "Yunlin": "99.73",
    "ChiaYiCounty": "45",
    "Pingtung": "289.57",
    "Taitung": "84.95",
    "Hualien": "1235.33",
    "Penghu": "159.08",
    "Keelung": "554.39",
    "HsinchuCity": "106.69",
    "ChiaYiCity": "92.31",
    "Kinmen": "115.59",
    "Matsu": "7.47"
}