{"Name":"å•†æ¥­ç™»è¨˜æ–°è¨­å®¶æ•¸","Unit":"å®¶","Explain":"æŒ‡ä¾å•†æ¥­ç™»è¨˜æ³•è¦å®šï¼Œå·²è¾¦å•†æ¥­ç™»è¨˜ä¹‹æ–°è¨­ç«‹å®¶æ•¸ã€‚","ByYear":97,"Total":"37481","Taiwan":"37461","NewTaipei":"6053","Taipei":"5641","Taoyuan":"3574","Taichung":"2413","Tainan":"1688","Kaohsiung":"4644","Ilan":"1044","HsinchuCounty":"686","Miaoli":"918","ChangHwa":"1441","Nantou":"678","Yunlin":"1019","ChiaYiCounty":"611","Pingtung":"433","Taitung":"718","Hualien":"263","Penghu":"626","Keelung":"865","HsinchuCity":"2158","ChiaYiCity":"1988","Kinmen":"20","Matsu":"-"}¾©å¸‚":"1988","é‡‘é–€ç¸£":"20","é€£æ±Ÿç¸£":"-"}