{
    "Name": "26歲人口數",
    "Unit": "人",
    "Explain": "於統計標準日戶籍登記實足年齡為26歲人口數。",
    "ByYear": 92,
    "Total": "379814",
    "Taiwan": "378569",
    "NewTaipei": "64986",
    "Taipei": "37050",
    "Taoyuan": "29740",
    "Taichung": "42478",
    "Tainan": "31422",
    "Kaohsiung": "49031",
    "Ilan": "7697",
    "HsinchuCounty": "7146",
    "Miaoli": "9100",
    "Changhwa": "24115",
    "Nantou": "8771",
    "Yunlin": "13277",
    "ChiaYiCounty": "9488",
    "Pingtung": "15869",
    "Taitung": "4037",
    "Hualien": "5916",
    "Penghu": "1612",
    "Keelung": "6474",
    "HsinchuCity": "6001",
    "ChiaYiCity": "4359",
    "Kinmen": "1099",
    "Matsu": "146"
}