{
    "Name": "食品衛生查驗與規定不符件數",
    "Unit": "件",
    "Explain": "與規定不符件數係以不符合衛生原因規定中不合規定項目原因予以分析並分別列計。",
    "ByYear": 89,
    "Total": "2961",
    "Taiwan": "2961",
    "NewTaipei": "372",
    "Taipei": "615",
    "Taoyuan": "90",
    "Taichung": "471",
    "Tainan": "396",
    "Kaohsiung": "250",
    "Ilan": "127",
    "HsinchuCounty": "98",
    "Miaoli": "43",
    "Changhwa": "13",
    "Nantou": "35",
    "Yunlin": "14",
    "ChiaYiCounty": "37",
    "Pingtung": "175",
    "Taitung": "-",
    "Hualien": "30",
    "Penghu": "22",
    "Keelung": "99",
    "HsinchuCity": "44",
    "ChiaYiCity": "30",
    "Kinmen": "-",
    "Matsu": "-"
}